Workbook

Sheet Front Sheet
I15: CONTRACT SUM ANALYSIS
I17: RELATING TO
I19: 10060 - EASTWOOD ESTATE NORTH
I21: AT
I23: EASTWOOD ESTATE
I24: LONDON N15

Sheet Cost Summary
A1: Cost Summary | C1: Cost Summary
C3: Ref | D3: Main Summary | E3: Total
C5: A | D5: PRELIMINARIES (Brought Forward) | E5: ='A1-Preliminaries'!H234 -> 1236865
C7: B | D7: DESIGN AND DEVELOPMENT COSTS (Brought Forward) | E7: ='B-Design and Development Costs'!D83 -> 0
C9: C | D9: DEMOLITIONS AND SITE CLEARANCE (Brought Forward) | E9: ='C-Demolition & Site Clearance'!D53 -> 90960.894
C11: D | D11: CONSTRUCTION COSTS
C13: D1 | D13: Building: Block N1: Passivhaus Classic (Brought Forward) | E13: ='D1 Building Block N1'!F272 -> 2304792.3
C15: D2 | D15: Building: Block N7: Passivhaus Low Energy (Brought Forward) | E15: ='D2 Building Block N7'!F244 -> 792157.31
C17: D3 | D17: Building: Community Clubroom Refurbishment (Brought Forward) | E17: ='D3 Clubroom Refurb'!F24 -> 31165
C19: D4 | D19: External Works to New Development (Brought Forward) | E19: ='D4 External Works'!D175 -> 712951.18
C22: E | D22: CONTRACTOR'S PROPOSALS (Brought Forward) | E22: ='E-Contractor''s Proposals'!D66 -> 0
C24: F | D24: WORKS OUTSIDE THE BOUNDARY OF THE SITE (Brought Forward) | E24: ='F-Works outside the boundary'!D46 -> 206521.51
C26: G | D26: AFTERCARE (Brought Forward) | E26: ='G-Aftercare'!D62 -> 0
D28: Sub-Total: Building Works | E28: =SUM(E4:E27) -> 5375413.2
C30: H | D30: OVERHEADS AND PROFIT
D32: The Contractor shall here insert the percentage adjustment required on expenditure against project variations and provisional sums where not measurable in line with the Contract Sum Analysis.
D33: Overhead: ………… % (please insert percentage) | E33: incl
D34: Profit: ………… % (please insert percentage) | E34: incl
C36: I | D36: PERFORMANCE BOND
D37: 10% to be allowed as per ER's | E37: 14474.682
C38: J | D38: CONTRACTOR’S INSURANCES | E38: 0
C40: K | D40: INSURANCE UNDER CONTRACT CLAUSE 6.5.1 | E40: 0
D42: Total Building Works | E42: =SUM(E28:E41) -> 5389887.9
D44: Below the line item:
C46: L | D46: ALTERNATIVE COSTS (Brought Forward) | E46: ='G-Aftercare'!D84 -> 0

Sheet Tender Instructions
A1: Instructions for tenders:
A3: 1 | B3: Bidders must fully price the item of these price schedule and ensure that their total tender price has been transferred correctly to the Cost Summary page and Form of Tender.
A5: 2 | B5: All cells must be completed.
A7: 3 | B7: All tender bids will be are evaluated and scored accordantly. Tenders with a deviation of 20% or more from the MEAN value will be required to provide further documentation to support there financial proposals.
A9: 4 | B9: Following confirmation of appointment, the winner tender could be required to provide further breakdown to there proposals.

Sheet Tender Qualifications
A1: Tender Qualifications:
B3: Please list any Tender Qualifications below:
A5: 1 | B5: Preliminaries
B6: Programme is based on a XXX month duration
B7: Assumes site compound for each site - N1 and N7
B8: Assumes 1no Welfare - complete with site Office, Canteen, Drying Room, Toilet Block, with other as a "satellite" - Portaloo and Office
B9: Assumes wet waste will be connected to existing sewage
B10: Allows for 1no Tower Crane to build N1, complete with hardstanding and all necessary ancillaries
B11: Alllows for 1no Telehandler to build N7
B12: No allowance for Oversail licence currently
B13: Scaffolding Monflex allowed only to N7 due to proximity of neighbours
B14: CCTV to be provided by monitored system, 2no locations - covering N1 and N7 compound
B15: Saftey Hoarding to be provided as timber, complete with sign boards (provided by others). Allowing for 1no Pedestrian Gate, 1no Vehicle Gate. No allowance for Biometric turnstile and the like
B16: Tree Protection to be erected and maintained for the duration of the contract, ownership remianing the responsibility of the contractor
B17: Tree Root Protection to Grounds will be installed and maintained for the duration of the contract, ownership remaining the responsibility of the contractor
A20: 2 | B20: Design and Development Costs
B21: Provisional Sums allowed only - due to information being requested for the Novation of contracts from design team
B22: Quotations for the Mains Services not received, as indicated from ITT ER's Clause 9.2.2
A25: 3 | B25: Demolition & Site Clearance
B26: Allows for demolition of existing Garages
B27: Allows for demolition of existing screen walls
B28: Allows for demolition of existing Muga
B29: Allows for area to be segregated whilst works are in progress
B30: Allows for works as seen and identiffied within the reports
A32: 4 | B32: Construction Works - Building Block N1, Building Block N7
B33: N1 - Piling Works allows for 46no piles, 450mm dia @ max depth of 18m. Subject to change on final piling designs
B34: N7 - Standard Trench Foundations
B35: N1 - to be constructed as a Reinforced Concrete Frame
B36: N7 - to be constructed as masonry construction with Hollowcore plank flooring
B37: Windows and Doors to be Aluminium - as specified Nordan Manufacturer
B38: Internal Specification as per Internal Schedule - 3849-LB-ZZ-ZZ-L-A-550020_Internal Finishes Schedule-C01
B39: No appliances allowed for in either block
A41: 5 | B41: Clubroom Refurb
B42: Provisional Sums allowed for at present - no details present
A44: 6 | B44: External Works
B45: Allows for all roads and paths as indetified within the civils and structural pack
B46: Allows for removal of Trees as identified on drawings
B47: Allows for New Soft Landscaping
B48: Allows for New Hardlandscaping
B49: Allows for New Street Furniture
B50: Allows for New Fencing
B51: Allows for EV Charger
A55: 7 | B55: Works Outside the boundary
B56: Assumes work to the middle of the Estate - in connection with the new footpath and Muga
B57: Assumes further works to estate roads, areas as highlighted on drawing 3849-LB-EN-XX-D-101000_C2_Works extent and Demolition Plan
A62: Tender Exclusions:
B64: Please list any Tender Exclusions below:
A66: 1 | B66: Tender is exclusive of VAT
A67: 2 | B67: All items within the garages to be disposed of by others
A68: 3 | B68: Contaminated Materials / Earth
A69: 4 | B69: Raingarden Planting
A70: 5 | B70: Service Diversions
A71: 6
A72: 7
A73: 8
A74: 9
A75: 10

Sheet A- Preliminaries Summary
A1: A1- Preliminaries Summary
A3: Ref | B3: Element | D3: Total
A5: A | B5: Site Accommodation | C5: £ | D5: ='A1-Preliminaries'!H42 -> 93578
A7: B | B7: Site Records | C7: £ | D7: ='A1-Preliminaries'!H46 -> 0
A9: C | B9: Completion and Post Completion Requirements | C9: £ | D9: ='A1-Preliminaries'!H62 -> 0
A11: D | B11: Management & Staff | C11: £ | D11: ='A1-Preliminaries'!H91 -> 431080
A13: E | B13: Temporary Services | C13: £ | D13: ='A1-Preliminaries'!H112 -> 111600
A15: F | B15: Scaffolding | C15: £ | D15: ='A1-Preliminaries'!H123 -> 222670
A17: G | B17: Security | C17: £ | D17: ='A1-Preliminaries'!H130 -> 16640
A19: H | B19: Safety & Environment Protection | C19: £ | D19: ='A1-Preliminaries'!H143 -> 73550
A21: I | B21: Control & Protection | C21: £ | D21: ='A1-Preliminaries'!H153 -> 9100
A23: J | B23: Mechanical Plant | C23: £ | D23: ='A1-Preliminaries'!H167 -> 137149
A25: K | B25: Temporary Works | C25: £ | D25: ='A1-Preliminaries'!H175 -> 0
A27: L | B27: Completion & Post Completion Requirement | C27: £ | D27: ='A1-Preliminaries'!H187 -> 69128
A29: M | B29: Cleaning | C29: £ | D29: ='A1-Preliminaries'!H198 -> 0
A31: N | B31: Fees and charges | C31: £ | D31: ='A1-Preliminaries'!H213 -> 10000
A33: O | B33: Insurance bonds | C33: £ | D33: ='A1-Preliminaries'!H231 -> 62370
A35: P | B35: Marketing | C35: £ | D35: ='A1-Preliminaries'!#REF! -> #REF!
B38: Preliminaries Total | C38: £ | D38: =SUM(D4:D37) -> #REF!

Sheet A1-Preliminaries
A1: A1- Cost Breakdown - Preliminaries
H2: Project Duration | I2: 52
A3: Contractors Proposed Programme Duration inclusive of lead in
A6: Ref | B6: Element | C6: Rate/week | D6: Number | E6: %age | F6: Weeks | H6: Total | I6: Comments
A8: A | B8: Site Accommodation
A9: 1 | B9: Office Accommodation | C9: =35+15 -> 50 | D9: 1 | E9: 1 | F9: =$I$2 -> 52 | G9: £ | H9: =C9*D9*E9*F9 -> 2600
A10: 2 | B10: Site Setup & establishment costs | C10: 10000 | D10: 1 | E10: 1 | F10: 1 | G10: £ | H10: =C10*D10*E10*F10 -> 10000 | I10: Fixed cost (not weekly) | J10: Assumes hardstanding
A11: 3 | B11: Site removal costs | C11: 2000 | D11: 1 | E11: 1 | F11: 1 | G11: £ | H11: =C11*D11*E11*F11 -> 2000 | I11: Fixed cost (not weekly)
A12: 4 | B12: Site reinstatement costs | G12: £ | H12: =C12*D12*E12*F12 -> 0 | I12: Fixed cost (not weekly)
A13: 5 | B13: Canteen units | C13: 35 | D13: 1 | E13: 1 | F13: =$I$2 -> 52 | G13: £ | H13: =C13*D13*E13*F13 -> 1820
A14: 6 | B14: Drying rooms | C14: 35 | D14: 2 | E14: 1 | F14: =$I$2 -> 52 | G14: £ | H14: =C14*D14*E14*F14 -> 3640
A15: 7 | B15: Toilet units | C15: 25 | D15: 2 | E15: 1 | F15: =$I$2 -> 52 | G15: £ | H15: =C15*D15*E15*F15 -> 2600
A16: 8 | B16: Transport & erect temp accommodation | C16: =850+110+14 -> 974 | D16: 4 | E16: 1 | F16: 1 | G16: £ | H16: =C16*D16*E16*F16 -> 3896
A17: 9 | B17: Furniture | C17: 16 | D17: 1 | E17: 1 | F17: =$I$2 -> 52 | G17: £ | H17: =C17*D17*E17*F17 -> 832
A18: 10 | B18: Fire extinguishers, fitting out & the like | F18: =$I$2 -> 52 | G18: £ | H18: =C18*D18*E18*F18 -> 0
A19: 11 | B19: Rates on temporary buildings | F19: =$I$2 -> 52 | G19: £ | H19: =C19*D19*E19*F19 -> 0
A20: 12 | B20: General Welfare consumables | C20: 215 | D20: 2 | E20: 1 | F20: =$I$2 -> 52 | G20: £ | H20: =C20*D20*E20*F20 -> 22360
A21: 13 | B21: Demobilisation costs | C21: 5000 | D21: 1 | E21: 1 | F21: 1 | G21: £ | H21: =C21*D21*E21*F21 -> 5000
A22: 14 | B22: Temp electrics - installation & equipment | F22: 1 | G22: £ | H22: =C22*D22*E22*F22 -> 0 | I22: Fixed cost (not weekly)
A23: 15 | B23: Temp water - ditto | F23: =$I$2 -> 52 | G23: £ | H23: =C23*D23*E23*F23 -> 0
A24: 16 | B24: Drainage temp connections | F24: 1 | G24: £ | H24: =C24*D24*E24*F24 -> 0 | I24: Fixed cost (not weekly)
A25: 17 | B25: Telephone installation | C25: 750 | D25: 1 | E25: 1 | F25: 1 | G25: £ | H25: =C25*D25*E25*F25 -> 750
A26: 18 | B26: Telephone rental & system charges | C26: 15 | D26: 1 | E26: 1 | F26: =$I$2 -> 52 | G26: £ | H26: =C26*D26*E26*F26 -> 780
A27: 19 | B27: IT Installations | C27: 100 | D27: 1 | E27: 1 | F27: =$I$2 -> 52 | G27: £ | H27: =C27*D27*E27*F27 -> 5200
A28: 20 | B28: Waste Management | C28: =350 -> 350 | D28: 1 | E28: 1 | F28: =$I$2 -> 52 | G28: £ | H28: =C28*D28*E28*F28 -> 18200
A29: 21 | B29: Condition surveys, records & photos | C29: 2500 | D29: 1 | E29: 1 | F29: 1 | G29: £ | H29: =C29*D29*E29*F29 -> 2500 | J29: Plugged
A30: 22 | B30: Progress Photography | C30: 25 | D30: 1 | E30: 1 | F30: =$I$2 -> 52 | G30: £ | H30: =C30*D30*E30*F30 -> 1300
A31: 23 | B31: Mobile phones | C31: 25 | D31: 2 | E31: 1 | F31: =$I$2 -> 52 | G31: £ | H31: =C31*D31*E31*F31 -> 2600
A32: 24 | B32: O&M manuals + As Built Drawings + completion packs | F32: 1 | G32: £ | H32: =C32*D32*E32*F32 -> 0 | J32: Check if these are done in house
A33: 25 | B33: Considerate Constructor Scheme | C33: 850 | D33: 1 | E33: 1 | F33: 1 | G33: £ | H33: =C33*D33*E33*F33 -> 850 | I33: Fixed cost (not weekly) | J33: Check considerate contractors
A34: 26 | B34: Petty cash | F34: 1 | G34: £ | H34: =C34*D34*E34*F34 -> 0 | I34: Fixed cost (not weekly)
A35: 27 | B35: SAP Rating calculation & certification | C35: 1650 | D35: 1 | E35: 1 | F35: 1 | G35: £ | H35: =C35*D35*E35*F35 -> 1650 | J35: Get rate from BSRIA
A36: 28 | B36: Passivhaus Liaison and documentation | C36: 5000 | D36: 1 | E36: 1 | F36: 1 | G36: £ | H36: =C36*D36*E36*F36 -> 5000 | I36: Fixed cost (not weekly) | J36: Plugged
A37: 29 | B37: (Contractor to state any additional items below) | G37: £ | H37: =C37*D37*E37*F37 -> 0
A38: 30 | G38: £ | H38: =C38*D38*E38*F38 -> 0
A39: 31 | G39: £ | H39: =C39*D39*E39*F39 -> 0
A40: 32 | G40: £ | H40: =C40*D40*E40*F40 -> 0
A41: 33 | G41: £ | H41: =C41*D41*E41*F41 -> 0
A42: A | B42: Section total: | G42: £ | H42: =SUM(H9:H41) -> 93578
A44: B | B44: Site Records
A45: 1 | B45: Site Records | D45: 1 | E45: 1 | G45: £ | H45: =C45*D45*E45*F45 -> 0 | I45: included
A46: B | B46: Section total: | G46: £ | H46: =SUM(H45) -> 0
A48: C | B48: Site Completion & post completion requirements
A49: 1 | B49: Handover requirements | D49: 1 | E49: 1 | F49: 1 | G49: £ | H49: =C49*D49*E49*F49 -> 0 | I49: Fixed cost (not weekly)
A50: 2 | B50: Operation and maintenance services | D50: 1 | E50: 1 | F50: 1 | G50: £ | H50: =C50*D50*E50*F50 -> 0 | I50: Fixed cost (not weekly)
A51: 3 | B51: Aftercare general management costs | D51: 1 | E51: 1 | F51: 1 | G51: £ | H51: =C51*D51*E51*F51 -> 0 | I51: Fixed cost (not weekly)
A52: 4 | B52: O & M Manuals production inc. Health and Safety files | D52: 1 | E52: 1 | F52: 1 | G52: £ | H52: =C52*D52*E52*F52 -> 0 | I52: Fixed cost (not weekly)
A53: 5 | B53: Suitably trained operative, with DBS clearance (ER's 1.19.2) | G53: £ | H53: =C53*D53*E53*F53 -> 0
A54: 6 | B54: Contractor allowance for one day’s induction (ER's 1.19.4) | D54: 1 | E54: 1 | G54: £ | H54: =C54*D54*E54*F54 -> 0
A55: 7 | B55: Post Completion handy person(s) (ER's 1.19.7) | D55: 1 | E55: 1 | G55: £ | H55: =C55*D55*E55*F55 -> 0
A56: 8 | B56: Testing & commissioning plan | G56: £ | H56: =C56*D56*E56*F56 -> 0
A57: 9 | B57: (Contractor to state any additional items below) | G57: £ | H57: =C57*D57*E57*F57 -> 0
D58: 1 | E58: 1 | G58: £ | H58: =C58*D58*E58*F58 -> 0
G59: £ | H59: =C59*D59*E59*F59 -> 0
G60: £ | H60: =C60*D60*E60*F60 -> 0
G61: £ | H61: =C61*D61*E61*F61 -> 0
A62: C | B62: Section total: | G62: £ | H62: =SUM(H49:H61) -> 0
L63: 8.5
A64: D | B64: Management & Staff | J64: Days | K64: Rate Per day | L64: hours
A65: 1 | B65: Contracts Manager | C65: =K65*5 -> 2250 | D65: 1 | E65: 0.6 | F65: =$I$2 -> 52 | G65: £ | H65: =C65*D65*E65*F65 -> 70200 | K65: 450 | L65: =K65/$L$63 -> 52.941176
A66: 2 | B66: Project Manager | C66: =K66*5 -> 2250 | D66: 1 | E66: 1 | F66: =$I$2 -> 52 | G66: £ | H66: =C66*D66*E66*F66 -> 117000 | K66: 450 | L66: =K66/$L$63 -> 52.941176
A67: 3 | B67: Site Manager | G67: £ | H67: =C67*D67*E67*F67 -> 0 | K67: 325 | L67: =K67/$L$63 -> 38.235294
A68: 4 | B68: Mechanical Manager | D68: 1 | E68: 1 | G68: £ | H68: =C68*D68*E68*F68 -> 0
A69: 5 | B69: Electrical Manager | D69: 1 | E69: 1 | G69: £ | H69: =C69*D69*E69*F69 -> 0
A70: 6 | B70: D&B Co-ordinator | D70: 1 | E70: 1 | G70: £ | H70: =C70*D70*E70*F70 -> 0
A71: 7 | B71: Planner | D71: 1 | E71: 1 | G71: £ | H71: =C71*D71*E71*F71 -> 0
A72: 8 | B72: Managing Surveyor | D72: 1 | E72: 1 | G72: £ | H72: =C72*D72*E72*F72 -> 0
A73: 9 | B73: Defects Rectification Period Manager | D73: 1 | E73: 1 | G73: £ | H73: =C73*D73*E73*F73 -> 0 | K73: 300 | L73: =K73/$L$63 -> 35.294118
A74: 10 | B74: Post Completion Manager | D74: 1 | E74: 1 | G74: £ | H74: =C74*D74*E74*F74 -> 0 | K74: 300 | L74: =K74/$L$63 -> 35.294118
A75: 11 | B75: Quantity Surveyor | C75: =K75*5 -> 2000 | D75: 1 | E75: 0.4 | F75: =$I$2 -> 52 | G75: £ | H75: =C75*D75*E75*F75 -> 41600 | K75: 400 | L75: =K75/$L$63 -> 47.058824
A76: 12 | B76: Secretarial & Admin | D76: 1 | E76: 1 | G76: £ | H76: =C76*D76*E76*F76 -> 0 | I76: included within OHP | K76: 225 | L76: =K76/$L$63 -> 26.470588
A77: 13 | B77: Security | G77: £ | H77: =C77*D77*E77*F77 -> 0 | I77: Managed by CCTV | K77: 225 | L77: =K77/$L$63 -> 26.470588
A78: 14 | B78: Finishing Foreman | G78: £ | H78: =C78*D78*E78*F78 -> 0 | K78: 250 | L78: =K78/$L$63 -> 29.411765
A79: 15 | B79: Health and Safety Manager | C79: =K79*5 -> 2500 | D79: 1 | E79: 0.2 | F79: =$I$2 -> 52 | G79: £ | H79: =C79*D79*E79*F79 -> 26000 | I79: based on 1 visit per week | K79: 500 | L79: =K79/$L$63 -> 58.823529
A80: 16 | B80: Setting Out Engineer | C80: =K80*5 -> 2500 | D80: 1 | E80: 0.2 | F80: 52 | G80: £ | H80: =C80*D80*E80*F80 -> 26000 | I80: based on 1 visit per week | K80: 500 | L80: =K80/$L$63 -> 58.823529
A81: 17 | B81: Multi Service Gang | D81: 1 | E81: 1 | G81: £ | H81: =C81*D81*E81*F81 -> 0
A82: 18 | B82: Traffic Marshall | C82: =K82*5 -> 807.5 | D82: 1 | E82: 1 | F82: =$I$2 -> 52 | G82: £ | H82: =C82*D82*E82*F82 -> 41990 | K82: =19*8.5 -> 161.5 | L82: =K82/$L$63 -> 19
A83: 19 | B83: Labourer | C83: =K83*5 -> 765 | D83: 1.5 | E83: 1 | F83: =$I$2 -> 52 | G83: £ | H83: =C83*D83*E83*F83 -> 59670 | K83: =18*8.5 -> 153 | L83: =K83/$L$63 -> 18
A84: 20 | B84: Gate / Banksman | G84: £ | H84: =C84*D84*E84*F84 -> 0 | K84: =19*8.5 -> 161.5 | L84: =K84/$L$63 -> 19
A85: 21 | B85: (Contractor to state any additional items below) | D85: 1 | E85: 1 | G85: £ | H85: =C85*D85*E85*F85 -> 0
A86: 22 | B86: Telehandler driver | C86: =K86*5 -> 935 | D86: 1 | E86: 1 | F86: =I2 -> 52 | G86: £ | H86: =C86*D86*E86*F86 -> 48620 | K86: =22*8.5 -> 187 | L86: 22
A87: 23 | B87: walkie talkies/gate huts | D87: 1 | E87: 1 | G87: £ | H87: =C87*D87*E87*F87 -> 0
A88: 24 | D88: 1 | E88: 1 | G88: £ | H88: =C88*D88*E88*F88 -> 0
A91: D | B91: Section total: | G91: £ | H91: =SUM(H65:H90) -> 431080
A93: E | B93: Temporary Services & Scaffolding
A94: 1 | B94: Temporary water supply | D94: 1 | E94: 1 | G94: £ | H94: =C94*D94*E94*F94 -> 0
A95: 2 | B95: Connections | D95: 1 | E95: 1 | F95: 1 | G95: £ | H95: =C95*D95*E95*F95 -> 0 | I95: Fixed cost (not weekly)
A96: 3 | B96: Metering | D96: 1 | E96: 1 | G96: £ | H96: =C96*D96*E96*F96 -> 0
A97: 4 | B97: Disconnection | D97: 1 | E97: 1 | F97: 1 | G97: £ | H97: =C97*D97*E97*F97 -> 0 | I97: Fixed cost (not weekly)
A98: 5 | B98: Stand pipe etc | D98: 1 | E98: 1 | G98: £ | H98: =C98*D98*E98*F98 -> 0
A99: 6 | B99: Consumption allowance (contractor responsible for actual usage) | C99: 250 | D99: 1 | E99: 1 | F99: =I2 -> 52 | G99: £ | H99: =C99*D99*E99*F99 -> 13000
A100: 7 | B100: Temporary gas supply | D100: 1 | E100: 1 | G100: £ | H100: =C100*D100*E100*F100 -> 0
A101: 8 | B101: Connections | D101: 1 | E101: 1 | F101: 1 | G101: £ | H101: =C101*D101*E101*F101 -> 0 | I101: Fixed cost (not weekly)
A102: 9 | B102: Metering | D102: 1 | E102: 1 | G102: £ | H102: =C102*D102*E102*F102 -> 0
A103: 10 | B103: Disconnection | D103: 1 | E103: 1 | F103: 1 | G103: £ | H103: =C103*D103*E103*F103 -> 0 | I103: Fixed cost (not weekly)
A104: 11 | B104: Consumption | D104: 1 | E104: 1 | G104: £ | H104: =C104*D104*E104*F104 -> 0
A105: 12 | B105: Temporary electric supply (inc. leads and transformers and all ancillary items for site wide distribution) | C105: 1800 | D105: 1 | E105: 1 | F105: =I2 -> 52 | G105: £ | H105: =C105*D105*E105*F105 -> 93600 | I105: assumes Generator to be used
A106: 13 | B106: Connections | D106: 1 | E106: 1 | F106: 1 | G106: £ | H106: =C106*D106*E106*F106 -> 0 | I106: Fixed cost (not weekly)
A107: 14 | B107: Metering | D107: 1 | E107: 1 | G107: £ | H107: =C107*D107*E107*F107 -> 0
A108: 15 | B108: Disconnection | D108: 1 | E108: 1 | F108: 1 | G108: £ | H108: =C108*D108*E108*F108 -> 0 | I108: Fixed cost (not weekly)
...

Sheet B-Design and Development Costs
A1: B - Cost Breakdown - Design and Development Costs
A3: Ref | B3: Element | D3: Total | H3: Cost | I3: 0.05 | J3: Rate to be used
B5: Design Team Fees
A6: 1 | B6: Architect
B7: Stage 4 - Technical Design | C7: £ | D7: =J7 -> 0 | I7: =H7*$I$3 -> 0 | J7: =SUM(H7:I7) -> 0 | K7: plugged - provisional
B8: Stage 5+ - Manufacturing and Construction | C8: £ | D8: =J8 -> 0 | I8: =H8*$I$3 -> 0 | J8: =SUM(H8:I8) -> 0
A10: 2 | B10: Structural Engineer | C10: £ | D10: =J10 -> 0 | I10: =H10*$I$3 -> 0 | J10: =SUM(H10:I10) -> 0
A13: 3 | B13: Mechanical and Electrical
B14: Stage 4 - Technical Design | C14: £ | D14: =J14 -> 0 | I14: =H14*$I$3 -> 0 | J14: =SUM(H14:I14) -> 0
B15: Stage 5 - Manufacturing and Construction | C15: £ | D15: =J15 -> 0 | I15: =H15*$I$3 -> 0 | J15: =SUM(H15:I15) -> 0
B16: Stage 6 - Handover | C16: £ | D16: =J16 -> 0 | I16: =H16*$I$3 -> 0 | J16: =SUM(H16:I16) -> 0
B17: Stage 7 - Use | C17: £ | D17: =J17 -> 0 | I17: =H17*$I$3 -> 0 | J17: =SUM(H17:I17) -> 0
A19: 4 | B19: Landscape Architect
B20: Stage 4 - Technical Design | C20: £ | D20: =J20 -> 0 | I20: =H20*$I$3 -> 0 | J20: =SUM(H20:I20) -> 0
B21: Stage 5 - Manufacturing and Construction | C21: £ | D21: =J21 -> 0 | I21: =H21*$I$3 -> 0 | J21: =SUM(H21:I21) -> 0
A23: 5 | B23: Other Designers - please specify
B24: Fire Engineer | C24: £ | D24: =J24 -> 0 | I24: =H24*$I$3 -> 0 | J24: =SUM(H24:I24) -> 0
B25: SAP assessor / incl. SAP, PEA & EPC certificates | C25: £ | D25: =J25 -> 0 | I25: =H25*$I$3 -> 0 | J25: =SUM(H25:I25) -> 0
C26: £ | D26: =J26 -> 0 | I26: =H26*$I$3 -> 0 | J26: =SUM(H26:I26) -> 0
B29: Local &Statutory Authority Costs
A30: 6 | B30: Planning Conditions | C30: £ | D30: =J30 -> 0 | I30: =H30*$I$3 -> 0 | J30: =SUM(H30:I30) -> 0
A31: 7 | B31: Building Control | C31: £ | D31: =J31 -> 0 | I31: =H31*$I$3 -> 0 | J31: =SUM(H31:I31) -> 0
A32: 8 | B32: Adoptable Works | C32: £ | D32: =J32 -> 0 | I32: =H32*$I$3 -> 0 | J32: =SUM(H32:I32) -> 0
A33: 9 | B33: Water Authority | C33: £ | D33: =J33 -> 0 | I33: =H33*$I$3 -> 0 | J33: =SUM(H33:I33) -> 0
A34: 10 | B34: UKPN | C34: £ | D34: =J34 -> 0 | I34: =H34*$I$3 -> 0 | J34: =SUM(H34:I34) -> 0
A35: 11 | B35: Gas | C35: £ | D35: =J35 -> 0 | I35: =H35*$I$3 -> 0 | J35: =SUM(H35:I35) -> 0
A36: 12 | B36: Highways inc. bonds | C36: £ | D36: =J36 -> 0 | I36: =H36*$I$3 -> 0 | J36: =SUM(H36:I36) -> 0
A37: 13 | B37: Section 106 | C37: £ | D37: =J37 -> 0 | I37: =H37*$I$3 -> 0 | J37: =SUM(H37:I37) -> 0
A38: 14 | B38: Section 104 | C38: £ | D38: =J38 -> 0 | I38: =H38*$I$3 -> 0 | J38: =SUM(H38:I38) -> 0
A39: 15 | B39: All other Local Authority cost:
B43: Site Surveys
A44: 16 | B44: Ground Investigations | C44: £ | D44: =J44 -> 0 | I44: =H44*$I$3 -> 0 | J44: =SUM(H44:I44) -> 0
A45: 17 | B45: Topographical | C45: £ | D45: =J45 -> 0 | I45: =H45*$I$3 -> 0 | J45: =SUM(H45:I45) -> 0
A46: 18 | B46: Asbestos | C46: £ | D46: =J46 -> 0 | I46: =H46*$I$3 -> 0 | J46: =SUM(H46:I46) -> 0
A47: 19 | B47: Ecological | C47: £ | D47: =J47 -> 0 | I47: =H47*$I$3 -> 0 | J47: =SUM(H47:I47) -> 0
A48: 20 | B48: Vibration & Noise Monitoring | C48: £ | D48: =J48 -> 0 | I48: =H48*$I$3 -> 0 | J48: =SUM(H48:I48) -> 0
B50: Certification
A51: 21 | B51: Energy Performance Certificates | C51: £ | D51: =J51 -> 0 | I51: =H51*$I$3 -> 0 | J51: =SUM(H51:I51) -> 0
A52: 22 | B52: Sound Tests | C52: £ | D52: =J52 -> 0 | I52: =H52*$I$3 -> 0 | J52: =SUM(H52:I52) -> 0
A53: 23 | B53: Air Tightness | C53: £ | D53: =J53 -> 0 | I53: =H53*$I$3 -> 0 | J53: =SUM(H53:I53) -> 0
A54: 24 | B54: RoSPA | C54: £ | D54: =J54 -> 0 | I54: =H54*$I$3 -> 0 | J54: =SUM(H54:I54) -> 0
C55: £ | D55: =J55 -> 0 | I55: =H55*$I$3 -> 0 | J55: =SUM(H55:I55) -> 0
B57: Carried Forward | C57: £ | D57: =SUM(D4:D55) -> 0
A58: Ref | B58: Element | D58: Total
B60: Brought Forward | D60: =D57 -> 0
B62: Insurances
A63: 25 | B63: Professional Indemnity | C63: £ | D63: =SUM(C63:C63) -> 0
A64: 26 | B64: Defects Insurance | C64: £ | D64: =SUM(C64:C64) -> 0
A65: 27 | B65: NHBC | C65: £ | D65: =SUM(C65:C65) -> 0
B67: Others
A68: 28 | B68: Party Wall | C68: £ | D68: =SUM(C68:C68) -> 0
A69: 29 | B69: All other Design and Development Costs required for the works | C69: £ | D69: =SUM(C69:C69) -> 0
A70: 30 | B70: Other Neighbourly | C70: £ | D70: =SUM(C70:C70) -> 0
A71: 31 | B71: CSC | C71: £ | D71: =SUM(C71:C71) -> 0
A72: 32 | B72: Crane oversail | C72: £ | D72: =SUM(C72:C72) -> 0
A73: 33 | B73: Other Design and Development Costs - please specify below: | C73: £ | D73: =SUM(C73:C73) -> 0
C74: £ | D74: =SUM(C74:C74) -> 0
C75: £ | D75: =SUM(C75:C75) -> 0
C76: £ | D76: =SUM(C76:C76) -> 0
C77: £ | D77: =SUM(C77:C77) -> 0
C78: £ | D78: =SUM(C78:C78) -> 0
C79: £ | D79: =SUM(C79:C79) -> 0
B83: Carried To Summary | C83: £ | D83: =SUM(D60:D82) -> 0

Sheet C-Demolition & Site Clearance
A1: C - Cost Breakdown - Demolitions and Site Clearance
A3: Ref | B3: Element | D3: Total | H3: Cost | I3: 0.15 | J3: Rate to be used
A5: 1 | B5: Demolition of structures on site | C5: £ | D5: =J5 -> 82335.894 | H5: 71596.43 | I5: =H5*I3 -> 10739.464 | J5: =SUM(H5:I5) -> 82335.894
A7: 2 | B7: Site Clearance | C7: £ | D7: incl
A9: 3 | B9: Remediation of contaminated earth | C9: £ | D9: excl
A11: 4 | B11: Excavation and levelling | C11: £ | D11: incl
A13: 5 | B13: All other demolitions and site clearance required for the works | C13: £ | D13: incl
A15: 6 | B15: Temporary works for demolition and site clearance | C15: £ | D15: incl
A17: 7 | B17: All other demolition works - Please specify below: | C17: £
A19: 8 | B19: Protection of existing block | C19: £ | D19: =J19 -> 8625 | H19: 7500 | I19: =H19*I3 -> 1125 | J19: =SUM(H19:I19) -> 8625 | K19: Provisional Sum
B53: Carried To Summary | C53: £ | D53: =SUM(D4:D52) -> 90960.894

Sheet D1 Building Block N1
A1: D1 - BUILDING: BLOCK N1 | M1: 5200
A3: Ref | B3: Element | D3: Elemental Total | F3: To Cost Summary | H3: Cost | I3: 0.15 | J3: Rate to be used
A5: 1 | B5: Substructure
A7: 1.1 | B7: Excavation works | C7: £ | D7: =J7 -> 6211.863 | H7: 5401.62 | I7: =H7*$I$3 -> 810.243 | J7: =SUM(H7:I7) -> 6211.863 | M7: =D7/$M$1 -> 1.194589
D8: =J8 -> 0 | M8: =D8/$M$1 -> 0
A9: 1.2 | B9: Standard foundations | D9: =J9 -> 0 | I9: =H9*$I$3 -> 0 | J9: =SUM(H9:I9) -> 0 | M9: =D9/$M$1 -> 0
D10: =J10 -> 0 | M10: =D10/$M$1 -> 0
A11: 1.3 | B11: Specialist foundations (piling mat, pile caps, pilling, etc.) | C11: £ | D11: =J11 -> 159775.16 | H11: =51519.92+87415 -> 138934.92 | I11: =H11*$I$3 -> 20840.238 | J11: =SUM(H11:I11) -> 159775.16 | M11: =D11/$M$1 -> 30.725992
D12: =J12 -> 0 | M12: =D12/$M$1 -> 0
A13: 1.3 | B13: Ground beams & ground floor slab | C13: £ | D13: =J13 -> 82671.637 | H13: 71888.38 | I13: =H13*$I$3 -> 10783.257 | J13: =SUM(H13:I13) -> 82671.637 | M13: =D13/$M$1 -> 15.898392
D14: =J14 -> 0 | M14: =D14/$M$1 -> 0
A15: 1.4 | B15: Retaining walls | C15: £ | D15: =J15 -> 0 | I15: =H15*$I$3 -> 0 | J15: =SUM(H15:I15) -> 0 | M15: =D15/$M$1 -> 0
D16: =J16 -> 0 | M16: =D16/$M$1 -> 0
A17: 1.5 | B17: Insulation | C17: £ | D17: =J17 -> 17733 | H17: 15420 | I17: =H17*$I$3 -> 2313 | J17: =SUM(H17:I17) -> 17733 | M17: =D17/$M$1 -> 3.4101923
D18: =J18 -> 0 | M18: =D18/$M$1 -> 0
A19: 1.6 | B19: All other substructure items and matters (please specify below): | D19: =J19 -> 0 | I19: =H19*$I$3 -> 0 | J19: =SUM(H19:I19) -> 0 | M19: =D19/$M$1 -> 0
B20: Lift pits | C20: £ | D20: =J20 -> 0 | I20: =H20*$I$3 -> 0 | J20: =SUM(H20:I20) -> 0 | M20: =D20/$M$1 -> 0
B21: Sundry works | C21: £ | D21: =J21 -> 270.25 | H21: 235 | I21: =H21*$I$3 -> 35.25 | J21: =SUM(H21:I21) -> 270.25 | M21: =D21/$M$1 -> 0.051971154
B22: Scaffold bases | C22: £ | D22: =J22 -> 0 | I22: =H22*$I$3 -> 0 | J22: =SUM(H22:I22) -> 0 | K22: Included within piling mat | M22: =D22/$M$1 -> 0
C23: £ | D23: =J23 -> 0 | I23: =H23*$I$3 -> 0 | J23: =SUM(H23:I23) -> 0 | M23: =D23/$M$1 -> 0
C24: £ | D24: =J24 -> 0 | I24: =H24*$I$3 -> 0 | J24: =SUM(H24:I24) -> 0 | M24: =D24/$M$1 -> 0
I25: =H25*$I$3 -> 0 | J25: =SUM(H25:I25) -> 0 | M25: =D25/$M$1 -> 0
D26: Substructure Sub-Total | E26: £ | F26: =SUM(D5:D24) -> 266661.91 | I26: =H26*$I$3 -> 0 | J26: =SUM(H26:I26) -> 0 | M26: =D26/$M$1 -> #VALUE!
I27: =H27*$I$3 -> 0 | J27: =SUM(H27:I27) -> 0 | M27: =D27/$M$1 -> 0
A28: 2 | B28: Superstructure | I28: =H28*$I$3 -> 0 | J28: =SUM(H28:I28) -> 0 | M28: =D28/$M$1 -> 0
I29: =H29*$I$3 -> 0 | J29: =SUM(H29:I29) -> 0 | M29: =D29/$M$1 -> 0
A30: 2.1 | B30: Frame | I30: =H30*$I$3 -> 0 | J30: =SUM(H30:I30) -> 0 | M30: =D30/$M$1 -> 0
M31: =D31/$M$1 -> 0
B32: Concrete frames - Ground Floor | C32: £ | D32: =J32 -> 0 | I32: =H32*$I$3 -> 0 | J32: =SUM(H32:I32) -> 0 | M32: =D32/$M$1 -> 0
A33: 2.1.2 | B33: Reinforced In-situ Concrete | C33: £ | D33: =J33 -> 4947.116 | H33: =2354.24+1498.15+449.45 -> 4301.84 | I33: =H33*$I$3 -> 645.276 | J33: =SUM(H33:I33) -> 4947.116 | M33: =D33/$M$1 -> 0.95136846
A34: 2.1.3 | B34: Formwork for Reinforced In-situ Concrete | C34: £ | D34: =J34 -> 12812.794 | H34: 11141.56 | I34: =H34*$I$3 -> 1671.234 | J34: =SUM(H34:I34) -> 12812.794 | M34: =D34/$M$1 -> 2.4639988
A35: 2.1.4 | B35: Reinforcement | C35: £ | D35: =J35 -> 5954.4125 | H35: 5177.75 | I35: =H35*$I$3 -> 776.6625 | J35: =SUM(H35:I35) -> 5954.4125 | M35: =D35/$M$1 -> 1.1450793
A36: 2.1.5 | B36: Concrete surface finishes | C36: £ | D36: =J36 -> 301.7025 | H36: 262.35 | I36: =H36*$I$3 -> 39.3525 | J36: =SUM(H36:I36) -> 301.7025 | M36: =D36/$M$1 -> 0.058019712
A37: 2.1.6 | B37: Forming holes (Diameter NE 150mm) | C37: £ | D37: =J37 -> 1207.5 | H37: =175*6 -> 1050 | I37: =H37*$I$3 -> 157.5 | J37: =SUM(H37:I37) -> 1207.5 | M37: =D37/$M$1 -> 0.23221154
B38: Concrete frames - First Floor | D38: =J38 -> 0 | M38: =D38/$M$1 -> 0
A39: 2.1.7 | B39: Reinforced In-situ Concrete | C39: £ | D39: =J39 -> 13607.766 | H39: 11832.84 | I39: =H39*$I$3 -> 1774.926 | J39: =SUM(H39:I39) -> 13607.766 | M39: =D39/$M$1 -> 2.6168781
A40: 2.1.8 | B40: Formwork for Reinforced In-situ Concrete | C40: £ | D40: =J40 -> 22969.824 | H40: 19973.76 | I40: =H40*$I$3 -> 2996.064 | J40: =SUM(H40:I40) -> 22969.824 | M40: =D40/$M$1 -> 4.4172738
A41: 2.1.9 | B41: Reinforcement | C41: £ | D41: =J41 -> 14826.087 | H41: 12892.25 | I41: =H41*$I$3 -> 1933.8375 | J41: =SUM(H41:I41) -> 14826.087 | M41: =D41/$M$1 -> 2.8511707
A42: 2.1.10 | B42: Concrete surface finishes | C42: £ | D42: =J42 -> 1449.0575 | H42: 1260.05 | I42: =H42*$I$3 -> 189.0075 | J42: =SUM(H42:I42) -> 1449.0575 | M42: =D42/$M$1 -> 0.2786649
A43: 2.1.11 | B43: Forming holes (Diameter NE 150mm) | C43: £ | D43: =J43 -> 1207.5 | H43: =175*6 -> 1050 | I43: =H43*$I$3 -> 157.5 | J43: =SUM(H43:I43) -> 1207.5 | M43: =D43/$M$1 -> 0.23221154
A44: 2.1.12 | B44: Steel Structure | C44: £ | D44: =J44 -> 1225.785 | H44: 1065.9 | I44: =H44*$I$3 -> 159.885 | J44: =SUM(H44:I44) -> 1225.785 | M44: =D44/$M$1 -> 0.23572788
A45: 2.1.13 | B45: Sundries | C45: £ | D45: =J45 -> 2213.612 | H45: 1924.88 | I45: =H45*$I$3 -> 288.732 | J45: =SUM(H45:I45) -> 2213.612 | M45: =D45/$M$1 -> 0.42569462
B46: Concrete frames - Second Floor | D46: =J46 -> 0 | M46: =D46/$M$1 -> 0
A47: 2.1.13 | B47: Reinforced In-situ Concrete | C47: £ | D47: =J47 -> 13607.766 | H47: 11832.84 | I47: =H47*$I$3 -> 1774.926 | J47: =SUM(H47:I47) -> 13607.766 | M47: =D47/$M$1 -> 2.6168781
A48: 2.1.14 | B48: Formwork for Reinforced In-situ Concrete | C48: £ | D48: =J48 -> 22969.824 | H48: 19973.76 | I48: =H48*$I$3 -> 2996.064 | J48: =SUM(H48:I48) -> 22969.824 | M48: =D48/$M$1 -> 4.4172738
A49: 2.1.15 | B49: Reinforcement | C49: £ | D49: =J49 -> 14826.087 | H49: 12892.25 | I49: =H49*$I$3 -> 1933.8375 | J49: =SUM(H49:I49) -> 14826.087 | M49: =D49/$M$1 -> 2.8511707
A50: 2.1.16 | B50: Concrete surface finishes | C50: £ | D50: =J50 -> 1449.0575 | H50: 1260.05 | I50: =H50*$I$3 -> 189.0075 | J50: =SUM(H50:I50) -> 1449.0575 | M50: =D50/$M$1 -> 0.2786649
A51: 2.1.17 | B51: Forming holes (Diameter NE 150mm) | C51: £ | D51: =J51 -> 1207.5 | H51: =175*6 -> 1050 | I51: =H51*$I$3 -> 157.5 | J51: =SUM(H51:I51) -> 1207.5 | M51: =D51/$M$1 -> 0.23221154
A52: 2.1.18 | B52: Sundries | C52: £ | D52: =J52 -> 2213.612 | H52: 1924.88 | I52: =H52*$I$3 -> 288.732 | J52: =SUM(H52:I52) -> 2213.612 | M52: =D52/$M$1 -> 0.42569462
B53: Concrete frames - Third Floor | D53: =J53 -> 0 | M53: =D53/$M$1 -> 0
A54: 2.1.19 | B54: Reinforced In-situ Concrete | C54: £ | D54: =J54 -> 13607.766 | H54: 11832.84 | I54: =H54*$I$3 -> 1774.926 | J54: =SUM(H54:I54) -> 13607.766 | M54: =D54/$M$1 -> 2.6168781
A55: 2.1.20 | B55: Formwork for Reinforced In-situ Concrete | C55: £ | D55: =J55 -> 22969.824 | H55: 19973.76 | I55: =H55*$I$3 -> 2996.064 | J55: =SUM(H55:I55) -> 22969.824 | M55: =D55/$M$1 -> 4.4172738
A56: 2.1.21 | B56: Reinforcement | C56: £ | D56: =J56 -> 14826.087 | H56: 12892.25 | I56: =H56*$I$3 -> 1933.8375 | J56: =SUM(H56:I56) -> 14826.087 | M56: =D56/$M$1 -> 2.8511707
A57: 2.1.22 | B57: Concrete surface finishes | C57: £ | D57: =J57 -> 1449.0575 | H57: 1260.05 | I57: =H57*$I$3 -> 189.0075 | J57: =SUM(H57:I57) -> 1449.0575 | M57: =D57/$M$1 -> 0.2786649
A58: 2.1.23 | B58: Forming holes (Diameter NE 150mm) | C58: £ | D58: =J58 -> 1207.5 | H58: =175*6 -> 1050 | I58: =H58*$I$3 -> 157.5 | J58: =SUM(H58:I58) -> 1207.5 | M58: =D58/$M$1 -> 0.23221154
A59: 2.1.24 | B59: Sundries | C59: £ | D59: =J59 -> 2213.612 | H59: 1924.88 | I59: =H59*$I$3 -> 288.732 | J59: =SUM(H59:I59) -> 2213.612 | M59: =D59/$M$1 -> 0.42569462
B60: Concrete frames - Forth Floor | D60: =J60 -> 0 | M60: =D60/$M$1 -> 0
A61: 2.1.25 | B61: Reinforced In-situ Concrete | C61: £ | D61: =J61 -> 13607.766 | H61: 11832.84 | I61: =H61*$I$3 -> 1774.926 | J61: =SUM(H61:I61) -> 13607.766 | M61: =D61/$M$1 -> 2.6168781
A62: 2.1.26 | B62: Formwork for Reinforced In-situ Concrete | C62: £ | D62: =J62 -> 23314.019 | H62: 20273.06 | I62: =H62*$I$3 -> 3040.959 | J62: =SUM(H62:I62) -> 23314.019 | M62: =D62/$M$1 -> 4.4834652
A63: 2.1.27 | B63: Reinforcement | C63: £ | D63: =J63 -> 14826.087 | H63: 12892.25 | I63: =H63*$I$3 -> 1933.8375 | J63: =SUM(H63:I63) -> 14826.087 | M63: =D63/$M$1 -> 2.8511707
A64: 2.1.28 | B64: Concrete surface finishes | C64: £ | D64: =J64 -> 1449.0575 | H64: 1260.05 | I64: =H64*$I$3 -> 189.0075 | J64: =SUM(H64:I64) -> 1449.0575 | M64: =D64/$M$1 -> 0.2786649
A65: 2.1.29 | B65: Forming holes (Diameter NE 150mm) | C65: £ | D65: =J65 -> 1207.5 | H65: =175*6 -> 1050 | I65: =H65*$I$3 -> 157.5 | J65: =SUM(H65:I65) -> 1207.5 | M65: =D65/$M$1 -> 0.23221154
A66: 2.1.30 | B66: Sundries | C66: £ | D66: =J66 -> 2213.612 | H66: 1924.88 | I66: =H66*$I$3 -> 288.732 | J66: =SUM(H66:I66) -> 2213.612 | M66: =D66/$M$1 -> 0.42569462
B67: Concrete frames - Roof Floor | D67: =J67 -> 0 | M67: =D67/$M$1 -> 0
A68: 2.1.31 | B68: Reinforced In-situ Concrete | C68: £ | D68: =J68 -> 9693.7985 | H68: 8429.39 | I68: =H68*$I$3 -> 1264.4085 | J68: =SUM(H68:I68) -> 9693.7985 | M68: =D68/$M$1 -> 1.864192
A69: 2.1.32 | B69: Formwork for Reinforced In-situ Concrete | C69: £ | D69: =J69 -> 21572.482 | H69: 18758.68 | I69: =H69*$I$3 -> 2813.802 | J69: =SUM(H69:I69) -> 21572.482 | M69: =D69/$M$1 -> 4.1485542
A70: 2.1.33 | B70: Reinforcement | C70: £ | D70: =J70 -> 9630.9625 | H70: 8374.75 | I70: =H70*$I$3 -> 1256.2125 | J70: =SUM(H70:I70) -> 9630.9625 | M70: =D70/$M$1 -> 1.8521082
A71: 2.1.34 | B71: Concrete surface finishes | C71: £ | D71: =J71 -> 2723.315 | H71: 2368.1 | I71: =H71*$I$3 -> 355.215 | J71: =SUM(H71:I71) -> 2723.315 | M71: =D71/$M$1 -> 0.52371442
A72: 2.1.35 | B72: Forming holes (Diameter NE 150mm) | C72: £ | D72: =J72 -> 1207.5 | H72: =175*6 -> 1050 | I72: =H72*$I$3 -> 157.5 | J72: =SUM(H72:I72) -> 1207.5 | M72: =D72/$M$1 -> 0.23221154
A73: 2.1.36 | B73: Sundries | C73: £ | D73: =J73 -> 1286.85 | H73: 1119 | I73: =H73*$I$3 -> 167.85 | J73: =SUM(H73:I73) -> 1286.85 | M73: =D73/$M$1 -> 0.24747115
D74: =J74 -> 0 | I74: =H74*$I$3 -> 0 | J74: =SUM(H74:I74) -> 0 | M74: =D74/$M$1 -> 0
A75: 2.2 | B75: Upper Floors | D75: =J75 -> 0 | I75: =H75*$I$3 -> 0 | J75: =SUM(H75:I75) -> 0 | M75: =D75/$M$1 -> 0
A76: 2.2.1 | B76: Concrete Floors | C76: £ | D76: =J76 -> 0 | I76: =H76*$I$3 -> 0 | J76: =SUM(H76:I76) -> 0 | M76: =D76/$M$1 -> 0
A77: 2.2.2 | B77: Balconies | C77: £ | D77: =J77 -> 6520.5 | H77: =90*9*7 -> 5670 | I77: =H77*$I$3 -> 850.5 | J77: =SUM(H77:I77) -> 6520.5 | M77: =D77/$M$1 -> 1.2539423
A78: 2.2.3 | B78: Drainage to balconies | C78: £ | D78: =J78 -> 0 | G78: inc above | I78: =H78*$I$3 -> 0 | J78: =SUM(H78:I78) -> 0 | M78: =D78/$M$1 -> 0
D79: =J79 -> 0 | I79: =H79*$I$3 -> 0 | J79: =SUM(H79:I79) -> 0 | M79: =D79/$M$1 -> 0
A80: 2.3 | B80: Roof | D80: =J80 -> 0 | I80: =H80*$I$3 -> 0 | J80: =SUM(H80:I80) -> 0 | M80: =D80/$M$1 -> 0
D81: =J81 -> 0 | M81: =D81/$M$1 -> 0
A82: 2.3.1 | B82: Roof structure | C82: £ | D82: =J82 -> 0 | G82: inc RC Frame | I82: =H82*$I$3 -> 0 | J82: =SUM(H82:I82) -> 0 | M82: =D82/$M$1 -> 0
A83: 2.3.2 | B83: Roof coverings | C83: £ | D83: =J83 -> 60568.2 | H83: 52668 | I83: =H83*$I$3 -> 7900.2 | J83: =SUM(H83:I83) -> 60568.2 | M83: =D83/$M$1 -> 11.647731
A84: 2.3.3 | B84: Insulation | D84: =J84 -> 0 | G84: inc above | I84: =H84*$I$3 -> 0 | J84: =SUM(H84:I84) -> 0 | M84: =D84/$M$1 -> 0
A85: 2.3.4 | B85: Roof drainage & All Rwg (Inc. Downpipes) | C85: £ | D85: =J85 -> 0 | I85: =H85*$I$3 -> 0 | J85: =SUM(H85:I85) -> 0 | M85: =D85/$M$1 -> 0
A86: 2.3.5 | B86: Mansafe system | C86: £ | D86: =J86 -> 6919.7685 | H86: =6017.19 -> 6017.19 | I86: =H86*$I$3 -> 902.5785 | J86: =SUM(H86:I86) -> 6919.7685 | M86: =D86/$M$1 -> 1.3307247
A87: 2.3.6 | B87: Extra over for green roof | C87: £ | D87: =J87 -> 10746.75 | H87: =6335+3010 -> 9345 | I87: =H87*$I$3 -> 1401.75 | J87: =SUM(H87:I87) -> 10746.75 | M87: =D87/$M$1 -> 2.0666827
D88: =J88 -> 0 | I88: =H88*$I$3 -> 0 | J88: =SUM(H88:I88) -> 0 | M88: =D88/$M$1 -> 0
A89: 2.4 | B89: Stairs & ramps | D89: =J89 -> 0 | I89: =H89*$I$3 -> 0 | J89: =SUM(H89:I89) -> 0 | M89: =D89/$M$1 -> 0
D90: =J90 -> 0 | M90: =D90/$M$1 -> 0
A91: 2.4.1 | B91: Stairs & ramps structures | C91: £ | D91: =J91 -> 20700 | H91: =4500*4 -> 18000 | I91: =H91*$I$3 -> 2700 | J91: =SUM(H91:I91) -> 20700 | K91: *Leci havent allowed for the forming of stairs, we will have to get a price for pre cast | M91: =D91/$M$1 -> 3.9807692
A92: 2.4.2 | B92: Stairs & ramps finishes | C92: £ | D92: =J92 -> 0 | G92: inc above | I92: =H92*$I$3 -> 0 | J92: =SUM(H92:I92) -> 0 | M92: =D92/$M$1 -> 0
A93: 2.4.3 | B93: Stairs & ramps balustrades and handrails | C93: £ | D93: =J93 -> 24048.846 | H93: =14922.6+5989.44 -> 20912.04 | I93: =H93*$I$3 -> 3136.806 | J93: =SUM(H93:I93) -> 24048.846 | M93: =D93/$M$1 -> 4.6247781
D94: =J94 -> 0 | I94: =H94*$I$3 -> 0 | J94: =SUM(H94:I94) -> 0 | M94: =D94/$M$1 -> 0
A95: 2.5 | B95: External Walls | D95: =J95 -> 0 | I95: =H95*$I$3 -> 0 | J95: =SUM(H95:I95) -> 0 | M95: =D95/$M$1 -> 0
D96: =J96 -> 0 | I96: =H96*$I$3 -> 0 | J96: =SUM(H96:I96) -> 0 | M96: =D96/$M$1 -> 0
A97: 2.5.1 | B97: External Enclosing Walls above ground level | C97: £ | D97: =J97 -> 211115.85 | H97: =134049+49530 -> 183579 | I97: =H97*$I$3 -> 27536.85 | J97: =SUM(H97:I97) -> 211115.85 | L97: bricklaying + materials | M97: =D97/$M$1 -> 40.599202
A98: 2.5.2 | B98: Insulation | C98: £ | D98: =J98 -> 233544.1 | H98: =203081.83 -> 203081.83 | I98: =H98*$I$3 -> 30462.274 | J98: =SUM(H98:I98) -> 233544.1 | M98: =D98/$M$1 -> 44.912328
A99: 2.5.3 | B99: Brick support to walls | C99: £ | D99: =J99 -> 19830.474 | H99: =17243.89 -> 17243.89 | I99: =H99*$I$3 -> 2586.5835 | J99: =SUM(H99:I99) -> 19830.474 | M99: =D99/$M$1 -> 3.8135526
A100: 2.5.4 | B100: Extra for façade embellishments (Raised brick bond detail; Perforated brick bond detail; etc..) | C100: £ | D100: =J100 -> 1709.475 | H100: 1486.5 | I100: =H100*$I$3 -> 222.975 | J100: =SUM(H100:I100) -> 1709.475 | L100: Render at £75 per m2 | M100: =D100/$M$1 -> 0.32874519
A101: 2.5.5 | B101: Concrete coping | C101: £ | D101: =J101 -> 8956.2115 | H101: =4422.66+526.8+351.35+1765.94+721.26 -> 7788.01 | I101: =H101*$I$3 -> 1168.2015 | J101: =SUM(H101:I101) -> 8956.2115 | M101: =D101/$M$1 -> 1.7223484
A102: 2.5.6 | B102: Precast elements | C102: £ | D102: =J102 -> 0 | I102: =H102*$I$3 -> 0 | J102: =SUM(H102:I102) -> 0 | K102: caststone | M102: =D102/$M$1 -> 0
A103: 2.5.7 | B103: Canopy - white concrete finish | C103: £ | D103: =J103 -> 36130.47 | H103: =9256.2+22161.6 -> 31417.8 | I103: =H103*$I$3 -> 4712.67 | J103: =SUM(H103:I103) -> 36130.47 | K103: currently priced as PPC Aluminimum | M103: =D103/$M$1 -> 6.9481673
...

Sheet D2 Building Block N7
A1: D2 - BUILDING: BLOCK N7
A3: Ref | B3: Element | D3: Elemental Total | F3: To Cost Summary | H3: Cost | I3: 0.15 | J3: Rate to be used
A5: 1 | B5: Substructure
A7: 1.1 | B7: Excavation works | C7: £ | D7: =J7 -> 16865.268 | H7: 14665.45 | I7: =H7*$I$3 -> 2199.8175 | J7: =SUM(H7:I7) -> 16865.268
D8: =J8 -> 0
A9: 1.2 | B9: Standard foundations | D9: =J9 -> 11969.43 | H9: =8290.8+1367+277.2+473.2 -> 10408.2 | I9: =H9*$I$3 -> 1561.23 | J9: =SUM(H9:I9) -> 11969.43
D10: =J10 -> 0
A11: 1.3 | B11: Specialist foundations (piling mat, pile caps, pilling, etc.) | C11: £ | D11: =J11 -> 0 | I11: =H11*$I$3 -> 0 | J11: =SUM(H11:I11) -> 0
D12: =J12 -> 0
A13: 1.3 | B13: Ground beams | C13: £ | D13: =J13 -> 0 | I13: =H13*$I$3 -> 0 | J13: =SUM(H13:I13) -> 0
D14: =J14 -> 0
A15: 1.4 | B15: Retaining walls | C15: £ | D15: =J15 -> 0 | I15: =H15*$I$3 -> 0 | J15: =SUM(H15:I15) -> 0
D16: =J16 -> 0
A17: 1.5 | B17: Ground floor slab | C17: £ | D17: =J17 -> 14520.59 | H17: 12626.6 | I17: =H17*$I$3 -> 1893.99 | J17: =SUM(H17:I17) -> 14520.59
D18: =J18 -> 0
A19: 1.6 | B19: Insulation | C19: £ | D19: =J19 -> 0 | I19: =H19*$I$3 -> 0 | J19: =SUM(H19:I19) -> 0
D20: =J20 -> 0 | I20: =H20*$I$3 -> 0 | J20: =SUM(H20:I20) -> 0
A21: 1.7 | B21: All other substructure items and matters (please specify below): | C21: £ | D21: =J21 -> 0 | I21: =H21*$I$3 -> 0 | J21: =SUM(H21:I21) -> 0
B22: Brickwork up to DPC | C22: £ | D22: =J22 -> 15588.342 | H22: 13555.08 | I22: =H22*$I$3 -> 2033.262 | J22: =SUM(H22:I22) -> 15588.342
B23: Blockwork up to DPC | C23: £ | D23: =J23 -> 7470.354 | H23: 6495.96 | I23: =H23*$I$3 -> 974.394 | J23: =SUM(H23:I23) -> 7470.354
B24: Scaffold bases | C24: £ | D24: =J24 -> 1779.096 | H24: 1547.04 | I24: =H24*$I$3 -> 232.056 | J24: =SUM(H24:I24) -> 1779.096
C25: £ | D25: =J25 -> 0 | I25: =H25*$I$3 -> 0 | J25: =SUM(H25:I25) -> 0
C26: £ | D26: =J26 -> 0 | I26: =H26*$I$3 -> 0 | J26: =SUM(H26:I26) -> 0
I27: =H27*$I$3 -> 0 | J27: =SUM(H27:I27) -> 0
D28: Substructure Sub-Total | E28: £ | F28: =SUM(D5:D26) -> 68193.08 | I28: =H28*$I$3 -> 0 | J28: =SUM(H28:I28) -> 0
I29: =H29*$I$3 -> 0 | J29: =SUM(H29:I29) -> 0
A30: 2 | B30: Superstructure | I30: =H30*$I$3 -> 0 | J30: =SUM(H30:I30) -> 0
I31: =H31*$I$3 -> 0 | J31: =SUM(H31:I31) -> 0
A32: 2.1 | B32: Frame | I32: =H32*$I$3 -> 0 | J32: =SUM(H32:I32) -> 0
I33: =H33*$I$3 -> 0 | J33: =SUM(H33:I33) -> 0
A34: 2.1.1 | B34: Steel frame | I34: =H34*$I$3 -> 0 | J34: =SUM(H34:I34) -> 0
A35: 2.1.1.1 | B35: Structural steel frame | C35: £ | D35: =J35 -> 42527.506 | H35: =18845.54+18134.9 -> 36980.44 | I35: =H35*$I$3 -> 5547.066 | J35: =SUM(H35:I35) -> 42527.506
A36: 2.1.1.2 | B36: Fire protection to steel frame | C36: £ | D36: =J36 -> 6465.99 | H36: 5622.6 | I36: =H36*$I$3 -> 843.39 | J36: =SUM(H36:I36) -> 6465.99
D37: =J37 -> 0 | I37: =H37*$I$3 -> 0 | J37: =SUM(H37:I37) -> 0
D38: =J38 -> 0 | I38: =H38*$I$3 -> 0 | J38: =SUM(H38:I38) -> 0
A39: 2.2 | B39: Upper Floors | D39: =J39 -> 0 | I39: =H39*$I$3 -> 0 | J39: =SUM(H39:I39) -> 0
D40: =J40 -> 0 | I40: =H40*$I$3 -> 0 | J40: =SUM(H40:I40) -> 0
A41: 2.2.1 | B41: Concrete Floors | C41: £ | D41: =J41 -> 0 | I41: =H41*$I$3 -> 0 | J41: =SUM(H41:I41) -> 0
B42: Hollocore precast floor | C42: £ | D42: =J42 -> 20731.05 | H42: 18027 | I42: =H42*$I$3 -> 2704.05 | J42: =SUM(H42:I42) -> 20731.05
B43: Insulation | C43: £ | D43: =J43 -> 0 | I43: =H43*$I$3 -> 0 | J43: =SUM(H43:I43) -> 0
D44: =J44 -> 0 | I44: =H44*$I$3 -> 0 | J44: =SUM(H44:I44) -> 0
A45: 2.2.2 | B45: Balconies | C45: £ | D45: =J45 -> 1449 | H45: =90*2*7 -> 1260 | I45: =H45*$I$3 -> 189 | J45: =SUM(H45:I45) -> 1449
D46: =J46 -> 0 | I46: =H46*$I$3 -> 0 | J46: =SUM(H46:I46) -> 0
A47: 2.2.3 | B47: Drainage to balconies | C47: £ | D47: =J47 -> 0 | G47: included above | I47: =H47*$I$3 -> 0 | J47: =SUM(H47:I47) -> 0
D48: =J48 -> 0 | I48: =H48*$I$3 -> 0 | J48: =SUM(H48:I48) -> 0
A49: 2.3 | B49: Roof | D49: =J49 -> 0 | I49: =H49*$I$3 -> 0 | J49: =SUM(H49:I49) -> 0
D50: =J50 -> 0 | I50: =H50*$I$3 -> 0 | J50: =SUM(H50:I50) -> 0
A51: 2.3.1 | B51: Roof structure | C51: £ | D51: =J51 -> 8625 | H51: 7500 | I51: =H51*$I$3 -> 1125 | J51: =SUM(H51:I51) -> 8625
A52: 2.3.2 | B52: Roof coverings | C52: £ | D52: =J52 -> 40292.55 | H52: 35037 | I52: =H52*$I$3 -> 5255.55 | J52: =SUM(H52:I52) -> 40292.55
A53: 2.3.3 | B53: Insulation | C53: £ | D53: =J53 -> 0 | I53: =H53*$I$3 -> 0 | J53: =SUM(H53:I53) -> 0
A54: 2.3.4 | B54: Roof drainage & All Rwg (Inc. Downpipes) | C54: £ | D54: =J54 -> 0 | G54: inc | I54: =H54*$I$3 -> 0 | J54: =SUM(H54:I54) -> 0
A55: 2.3.5 | B55: Mansafe system | C55: £ | D55: =J55 -> 0 | G55: not required | I55: =H55*$I$3 -> 0 | J55: =SUM(H55:I55) -> 0
D56: =J56 -> 0 | I56: =H56*$I$3 -> 0 | J56: =SUM(H56:I56) -> 0
D57: =J57 -> 0 | I57: =H57*$I$3 -> 0 | J57: =SUM(H57:I57) -> 0
A58: 2.4 | B58: Stairs & ramps | D58: =J58 -> 0 | I58: =H58*$I$3 -> 0 | J58: =SUM(H58:I58) -> 0 | L58: Metal Contractor to price
D59: =J59 -> 0 | I59: =H59*$I$3 -> 0 | J59: =SUM(H59:I59) -> 0
A60: 2.4.1 | B60: Stairs & ramps structures | C60: £ | D60: =J60 -> 27730.203 | H60: =7896+5060.1+11157.12 -> 24113.22 | I60: =H60*$I$3 -> 3616.983 | J60: =SUM(H60:I60) -> 27730.203
A61: 2.4.2 | B61: Stairs & ramps finishes | C61: £ | D61: =J61 -> 0 | I61: =H61*$I$3 -> 0 | J61: =SUM(H61:I61) -> 0
A62: 2.4.3 | B62: Stairs & ramps balustrades and handrails | C62: £ | D62: =J62 -> 5245.955 | H62: =4561.7 -> 4561.7 | I62: =H62*$I$3 -> 684.255 | J62: =SUM(H62:I62) -> 5245.955
A63: 2.4.4 | B63: Soffits | C63: £ | D63: =J63 -> 33377.715 | H63: 29024.1 | I63: =H63*$I$3 -> 4353.615 | J63: =SUM(H63:I63) -> 33377.715
A64: 2.4.5 | B64: Demolition of existing staircase | C64: £ | D64: =J64 -> 5750 | H64: 5000 | I64: =H64*$I$3 -> 750 | J64: =SUM(H64:I64) -> 5750 | L64: Plugged rate
A65: 2.4.6 | B65: Making good removal areas on existing building | C65: £ | D65: =J65 -> 5750 | H65: 5000 | I65: =H65*$I$3 -> 750 | J65: =SUM(H65:I65) -> 5750 | L65: Plugged rate
D66: =J66 -> 0 | I66: =H66*$I$3 -> 0 | J66: =SUM(H66:I66) -> 0
A67: 2.5 | B67: External Walls | D67: =J67 -> 0 | I67: =H67*$I$3 -> 0 | J67: =SUM(H67:I67) -> 0
D68: =J68 -> 0 | I68: =H68*$I$3 -> 0 | J68: =SUM(H68:I68) -> 0
A69: 2.5.1 | B69: External Enclosing Walls above ground level | C69: £ | D69: =J69 -> 141882.88 | H69: =1381.42+80543+31012+10440 -> 123376.42 | I69: =H69*$I$3 -> 18506.463 | J69: =SUM(H69:I69) -> 141882.88 | L69: Concrete Lintels + Bricklaying + materials
A70: 2.5.2 | B70: Insulation | C70: £ | D70: =J70 -> 0 | G70: inc | I70: =H70*$I$3 -> 0 | J70: =SUM(H70:I70) -> 0
A71: 2.5.3 | B71: Brick support to walls | C71: £ | D71: =J71 -> 0 | G71: not required | I71: =H71*$I$3 -> 0 | J71: =SUM(H71:I71) -> 0
A72: 2.5.4 | B72: Extra for façade embellishments (Raised brick bond detail; Perforated brick bond detail; etc..) | C72: £ | D72: =J72 -> 0 | G72: inc | I72: =H72*$I$3 -> 0 | J72: =SUM(H72:I72) -> 0
A73: 2.5.5 | B73: Concrete coping | C73: £ | D73: =J73 -> 8352.795 | H73: =5561.71+556.16+463.53+681.9 -> 7263.3 | I73: =H73*$I$3 -> 1089.495 | J73: =SUM(H73:I73) -> 8352.795
A74: 2.5.6 | B74: Precast concrete strip | C74: £ | D74: =J74 -> 0 | I74: =H74*$I$3 -> 0 | J74: =SUM(H74:I74) -> 0
A75: 2.5.7 | B75: 215mm Brick wall | C75: £ | D75: =J75 -> 0 | I75: =H75*$I$3 -> 0 | J75: =SUM(H75:I75) -> 0
D76: =J76 -> 0 | I76: =H76*$I$3 -> 0 | J76: =SUM(H76:I76) -> 0
A77: 2.5.8 | B77: Private Balconies, terraces, staircase | D77: =J77 -> 0 | I77: =H77*$I$3 -> 0 | J77: =SUM(H77:I77) -> 0
A78: 2.5.8.1 | B78: Balcony - Hollocore precast floor 150mm include finishings, decking inc. insulation and thermal breaks cast to upper floor slabs | C78: £ | D78: =J78 -> 1811.25 | G78: included in PCC Paving and decking pedestals | H78: 1575 | I78: =H78*$I$3 -> 236.25 | J78: =SUM(H78:I78) -> 1811.25
A79: 2.5.8.2 | B79: Metal open balustrades to balconies and terraces | C79: £ | D79: =J79 -> 6315.0525 | H79: =1858.73+3632.62 -> 5491.35 | I79: =H79*$I$3 -> 823.7025 | J79: =SUM(H79:I79) -> 6315.0525
A80: 2.5.8.3 | B80: Staircase Canopy | C80: £ | D80: =J80 -> 23589.375 | H80: 20512.5 | I80: =H80*$I$3 -> 3076.875 | J80: =SUM(H80:I80) -> 23589.375
A81: 2.5.8.4 | B81: Steel balustrades - refuse area | C81: £ | D81: =J81 -> 4677.763 | H81: =1271.62+2796 -> 4067.62 | I81: =H81*$I$3 -> 610.143 | J81: =SUM(H81:I81) -> 4677.763
D82: =J82 -> 0 | I82: =H82*$I$3 -> 0 | J82: =SUM(H82:I82) -> 0
A83: 2.6 | B83: Window and external doors | D83: =J83 -> 0 | G83: NORDAN manufacturer | I83: =H83*$I$3 -> 0 | J83: =SUM(H83:I83) -> 0
D84: =J84 -> 0 | I84: =H84*$I$3 -> 0 | J84: =SUM(H84:I84) -> 0
A85: 2.6.1 | B85: External windows | D85: =J85 -> 0 | I85: =H85*$I$3 -> 0 | J85: =SUM(H85:I85) -> 0
A86: 2.6.1.1 | B86: Triple glazed aluminium composite windows | C86: £ | D86: =J86 -> 20690.674 | H86: =400.25+252.38+1556.22+252.38+400.25+113.18+(3*436.91)+(5*718.64)+479.91+(2*802.3)+345.09+996.86+37.56+(2*1320.73)+(951.62)+(2*1102.72)+(2*171.17)+(2*39.66)+(63.91)+(2*38.66)+(5*31.4)+(24.27)+(3*21.32)+(2*21.32) -> 17991.89 | I86: =H86*$I$3 -> 2698.7835 | J86: =SUM(H86:I86) -> 20690.674 | L86: Supply Only
A87: 2.6.1.2 | B87: Metal shutters | C87: £ | D87: =J87 -> 13800 | H87: =16*750 -> 12000 | I87: =H87*$I$3 -> 1800 | J87: =SUM(H87:I87) -> 13800
D88: =J88 -> 0 | I88: =H88*$I$3 -> 0 | J88: =SUM(H88:I88) -> 0
A89: 2.6.2 | B89: External doors | D89: =J89 -> 0 | I89: =H89*$I$3 -> 0 | J89: =SUM(H89:I89) -> 0
A90: 2.6.2.1 | B90: External doors to apartments | C90: £ | D90: =J90 -> 0 | G90: inc | I90: =H90*$I$3 -> 0 | J90: =SUM(H90:I90) -> 0
A91: 2.6.2.2 | B91: Metal doors - Louvre over panel | C91: £ | D91: =J91 -> 2156.25 | H91: =1750+125 -> 1875 | I91: =H91*$I$3 -> 281.25 | J91: =SUM(H91:I91) -> 2156.25
A92: 2.6.2.3 | B92: Balcony door shutters | C92: £ | D92: =J92 -> 1150 | G92: inc | H92: 1000 | I92: =H92*$I$3 -> 150 | J92: =SUM(H92:I92) -> 1150
A93: 2.6.2.4 | B93: Double doors | C93: £ | D93: =J93 -> 0 | G93: inc | I93: =H93*$I$3 -> 0 | J93: =SUM(H93:I93) -> 0
A94: 2.6.2.5 | B94: Single doors | C94: £ | D94: =J94 -> 0 | G94: inc | I94: =H94*$I$3 -> 0 | J94: =SUM(H94:I94) -> 0
A95: 2.6.2.6 | B95: Riser doors | C95: £ | D95: =J95 -> 4025 | H95: =1500+(1000*2) -> 3500 | I95: =H95*$I$3 -> 525 | J95: =SUM(H95:I95) -> 4025
A96: 2.6.2.7 | B96: Side Gate | D96: =J96 -> 3289 | H96: 2860 | I96: =H96*$I$3 -> 429 | J96: =SUM(H96:I96) -> 3289
D97: =J97 -> 0
A98: 2.7 | B98: Internal Walls and Partitions | D98: =J98 -> 0 | I98: =H98*$I$3 -> 0 | J98: =SUM(H98:I98) -> 0
D99: =J99 -> 0 | I99: =H99*$I$3 -> 0 | J99: =SUM(H99:I99) -> 0
A100: 2.7.1 | B100: Walls and Partitions - Party Walls and Communal Walls | C100: £ | D100: =J100 -> 8839.4175 | H100: 7686.45 | I100: =H100*$I$3 -> 1152.9675 | J100: =SUM(H100:I100) -> 8839.4175
A101: 2.7.2 | B101: Walls and Partitions - Partitions | C101: £ | D101: =J101 -> 12868.834 | H101: 11190.29 | I101: =H101*$I$3 -> 1678.5435 | J101: =SUM(H101:I101) -> 12868.834
D102: =J102 -> 0 | I102: =H102*$I$3 -> 0 | J102: =SUM(H102:I102) -> 0
A103: 2.8 | B103: Internal Doors | D103: =J103 -> 0 | I103: =H103*$I$3 -> 0 | J103: =SUM(H103:I103) -> 0
...

Sheet D3 Clubroom Refurb
A1: D2 - BUILDING: BLOCK N7
A3: Ref | B3: Element | D3: Elemental Total | F3: To Cost Summary | H3: Cost | I3: 0.15 | J3: Rate to be used
A5: 7 | B5: Refurbishment Works
B6: Community Clubroom
A8: 1.1 | B8: Remove razor wire. | C8: £ | D8: =J8 -> 1725 | H8: 1500 | I8: =H8*$I$3 -> 225 | J8: =SUM(H8:I8) -> 1725
A10: 1.2 | B10: All front, rear and some upper windows all need to be replaced (high security and controlled/restricted opening), with high quality toughened/laminated and high efficient double glazed units. | C10: £ | D10: =J10 -> 20700 | H10: =900*20 -> 18000 | I10: =H10*$I$3 -> 2700 | J10: =SUM(H10:I10) -> 20700
A12: 1.3 | B12: Fanlight windows to be bricked up. | C12: £ | D12: =J12 -> 2587.5 | H12: =450*5 -> 2250 | I12: =H12*$I$3 -> 337.5 | J12: =SUM(H12:I12) -> 2587.5 | M12: £450 per opening x 5
A14: 1.4 | B14: Remove and replace the existing plain main entrance security door and surround should be replaced with high security door entrance door. | C14: £ | D14: =J14 -> 2012.5 | H14: 1750 | I14: =H14*$I$3 -> 262.5 | J14: =SUM(H14:I14) -> 2012.5 | M14: £1500 for security door
A16: 1.5 | B16: Replacment of street lighting. | C16: £ | D16: =J16 -> 4140 | H16: 3600 | I16: =H16*$I$3 -> 540 | J16: =SUM(H16:I16) -> 4140
D21: Substructure Sub-Total | E21: £ | F21: =SUM(D5:D19) -> 31165
D24: Carried To Summary | E24: £ | F24: =F21 -> 31165

Sheet D4 External Works
A1: D3 - External Works to New Development
A3: A | B3: Pricing notes on external works
B4: - Tenders are required to price all individual items listed below
A7: Ref | B7: Element | D7: Total | H7: Cost | I7: 0.15 | J7: Rate to be used
A9: 8.1 | B9: Site Preparation Works
A10: 8.1.1 | B10: Site clearance | C10: £ | D10: =J10 -> 0 | E10: included elsewhere | I10: =H10*$I$7 -> 0 | J10: =SUM(H10:I10) -> 0
A11: 8.1.2 | B11: Excavation and levelling | C11: £ | D11: =J11 -> 0 | I11: =H11*$I$7 -> 0 | J11: =SUM(H11:I11) -> 0
A12: 8.1.3 | B12: Tree removal | C12: £ | D12: =J12 -> 0 | I12: =H12*$I$7 -> 0 | J12: =SUM(H12:I12) -> 0
A13: 8.1.4 | B13: Trees protection | C13: £ | D13: =J13 -> 0 | I13: =H13*$I$7 -> 0 | J13: =SUM(H13:I13) -> 0
A14: 8.1.5 | B14: Minor demolition works | C14: £ | D14: =J14 -> 0 | I14: =H14*$I$7 -> 0 | J14: =SUM(H14:I14) -> 0
B15: Remove existing infill brick wall | C15: £ | D15: =J15 -> 0 | E15: included elsewhere | I15: =H15*$I$7 -> 0 | J15: =SUM(H15:I15) -> 0
B16: Remove existing play equipment and set aside for reuse. | C16: £ | D16: =J16 -> 0 | E16: included elsewhere | I16: =H16*$I$7 -> 0 | J16: =SUM(H16:I16) -> 0
B17: Remove BT telephone box, existing railings | C17: £ | D17: =J17 -> 0 | E17: included elsewhere | I17: =H17*$I$7 -> 0 | J17: =SUM(H17:I17) -> 0
D18: =J18 -> 0 | I18: =H18*$I$7 -> 0 | J18: =SUM(H18:I18) -> 0
D19: =J19 -> 0 | I19: =H19*$I$7 -> 0 | J19: =SUM(H19:I19) -> 0
A20: 8.2 | B20: Roads, Paths, Pavings and Surfacing | D20: =J20 -> 0 | I20: =H20*$I$7 -> 0 | J20: =SUM(H20:I20) -> 0
A21: 8.2.1 | B21: P01 Tarmac - N7 | C21: £ | D21: =J21 -> 13816.135 | H21: =11969.78+44.25 -> 12014.03 | I21: =H21*$I$7 -> 1802.1045 | J21: =SUM(H21:I21) -> 13816.135 | K21: LECI
A22: 8.2.2 | B22: P02a Impermeable coloured asphalt - N1 | C22: £ | D22: =J22 -> 23564.535 | H22: 20490.9 | I22: =H22*$I$7 -> 3073.635 | J22: =SUM(H22:I22) -> 23564.535 | K22: LECI
A23: 8.2.3 | B23: P02a Impermeable coloured asphalt - N7 | C23: £ | D23: =J23 -> 17638.631 | H23: 15337.94 | I23: =H23*$I$7 -> 2300.691 | J23: =SUM(H23:I23) -> 17638.631 | K23: LECI
A24: 8.2.4 | B24: P02b Permeable coloured asphalt | C24: £ | D24: =J24 -> 7607.8595 | H24: 6615.53 | I24: =H24*$I$7 -> 992.3295 | J24: =SUM(H24:I24) -> 7607.8595 | K24: LECI
A25: 8.2.5 | B25: Resurface new road - remove existing & resurface | C25: £ | D25: =J25 -> 36773.55 | H25: 31977 | I25: =H25*$I$7 -> 4796.55 | J25: =SUM(H25:I25) -> 36773.55
A26: 8.2.6 | B26: P04 Wet pour play safety surface | C26: £ | D26: =J26 -> 60570.477 | H26: =13992.78+38677.2 -> 52669.98 | I26: =H26*$I$7 -> 7900.497 | J26: =SUM(H26:I26) -> 60570.477
A27: 8.2.7 | B27: P03 Playground surface - Break up existing surface | C27: £ | D27: =J27 -> 0 | I27: =H27*$I$7 -> 0 | J27: =SUM(H27:I27) -> 0
A28: 8.2.8 | B28: P03 Upgraded MUGA surface | C28: £ | D28: =J28 -> 52957.5 | E28: Prov Sum | H28: =150*307 -> 46050 | I28: =H28*$I$7 -> 6907.5 | J28: =SUM(H28:I28) -> 52957.5
A29: 8.2.9 | B29: Painting existing Muga | C29: £ | D29: =J29 -> 0 | I29: =H29*$I$7 -> 0 | J29: =SUM(H29:I29) -> 0
A30: 8.2.10 | B30: P05 PCC flag pavers - N1 | C30: £ | D30: =J30 -> 3176.438 | H30: 2762.12 | I30: =H30*$I$7 -> 414.318 | J30: =SUM(H30:I30) -> 3176.438 | K30: LECI
A31: 8.2.11 | B31: P05 PCC flag pavers - N7 | C31: £ | D31: =J31 -> 4557.496 | H31: 3963.04 | I31: =H31*$I$7 -> 594.456 | J31: =SUM(H31:I31) -> 4557.496 | K31: LECI
A32: 8.2.12 | B32: Zebra crossing allowance | C32: £ | D32: =J32 -> 1725 | H32: 1500 | I32: =H32*$I$7 -> 225 | J32: =SUM(H32:I32) -> 1725 | K32: plugged rate
A33: 8.2.13 | B33: New footpath | C33: £ | D33: =J33 -> 3677.7 | H33: 3198 | I33: =H33*$I$7 -> 479.7 | J33: =SUM(H33:I33) -> 3677.7
A34: 8.2.14 | B34: Car Parking | C34: £ | D34: =J34 -> 23872.792 | H34: 20758.95 | I34: =H34*$I$7 -> 3113.8425 | J34: =SUM(H34:I34) -> 23872.792
A35: 8.2.15 | B35: PCC Kerb - N1 | C35: £ | D35: =J35 -> 2408.951 | H35: 2094.74 | I35: =H35*$I$7 -> 314.211 | J35: =SUM(H35:I35) -> 2408.951 | K35: LECI
A36: 8.2.16 | B36: PCC Edging - N1 | C36: £ | D36: =J36 -> 2949.75 | H36: =2565 -> 2565 | I36: =H36*$I$7 -> 384.75 | J36: =SUM(H36:I36) -> 2949.75 | K36: LECI
A37: 8.2.17 | B37: PCC Kerb - N7 | C37: £ | D37: =J37 -> 5047.35 | H37: 4389 | I37: =H37*$I$7 -> 658.35 | J37: =SUM(H37:I37) -> 5047.35 | K37: LECI
A38: 8.2.18 | B38: PCC Edging - N7 | C38: £ | D38: =J38 -> 2979.2475 | H38: 2590.65 | I38: =H38*$I$7 -> 388.5975 | J38: =SUM(H38:I38) -> 2979.2475 | K38: LECI
D39: =J39 -> 0 | I39: =H39*$I$7 -> 0 | J39: =SUM(H39:I39) -> 0
D40: =J40 -> 0 | I40: =H40*$I$7 -> 0 | J40: =SUM(H40:I40) -> 0
A41: 8.3 | B41: Soft Landscaping, Planting and Irrigation Systems | D41: =J41 -> 0 | I41: =H41*$I$7 -> 0 | J41: =SUM(H41:I41) -> 0
A42: 8.3.1 | B42: PL01 Defensible buffer planting | C42: £ | D42: =J42 -> 12309.014 | H42: =338.91+1007.49+274.13+379.99+960.63+864.07+2140.65+939.33+864.07+957.08+948.56+301.78+377.62+349.18 -> 10703.49 | I42: =H42*$I$7 -> 1605.5235 | J42: =SUM(H42:I42) -> 12309.014
A43: 8.3.2 | B43: PL02 - Suds Planting | C43: £ | D43: =J43 -> 16210.032 | H43: =638.4+1324.8+819.2+904+771.2+747.2+2080.8+2659.68+1958.4+780.8+632+779.2 -> 14095.68 | I43: =H43*$I$7 -> 2114.352 | J43: =SUM(H43:I43) -> 16210.032
A44: 8.3.3 | B44: PL03 Boundary Planting | C44: £ | D44: =J44 -> 15953.743 | H44: =444.05+541.08+435.49+314.28+318.86+459.03+463.32+333.72+459.03+426.6+459.03+542.49+459.03+677.31+476.15+7063.35 -> 13872.82 | I44: =H44*$I$7 -> 2080.923 | J44: =SUM(H44:I44) -> 15953.743
A45: 8.3.4 | B45: PL04 Amenity Grass | C45: £ | D45: =J45 -> 4449.2925 | H45: =435.2+278.69+18.56+2767.5+369 -> 3868.95 | I45: =H45*$I$7 -> 580.3425 | J45: =SUM(H45:I45) -> 4449.2925
A46: 8.3.5 | B46: PL05 Vertical greening | C46: £ | D46: =J46 -> 2021.355 | H46: =248.85+248.85+248.85+157.95+203.13+127.62+522.45 -> 1757.7 | I46: =H46*$I$7 -> 263.655 | J46: =SUM(H46:I46) -> 2021.355
A47: 8.3.6 | B47: EO raingarden planting for SUDS | C47: £ | D47: =J47 -> 0 | I47: =H47*$I$7 -> 0 | J47: =SUM(H47:I47) -> 0
A48: 8.3.7 | B48: Existing trees to prune | C48: £ | D48: =J48 -> 5175 | H48: =500*9 -> 4500 | I48: =H48*$I$7 -> 675 | J48: =SUM(H48:I48) -> 5175 | K48: plugged rate
A49: 8.3.8 | B49: New proposed trees ,18-20cm girth | C49: £ | D49: =J49 -> 3677.861 | H49: =515.86+939.72+1094.56+((720+576)/2) -> 3198.14 | I49: =H49*$I$7 -> 479.721 | J49: =SUM(H49:I49) -> 3677.861
A50: 8.3.9 | B50: New proposed trees, 12-14cm girth | C50: £ | D50: =J50 -> 2685.342 | H50: =496.4+283.8+906.88+((720+576)/2) -> 2335.08 | I50: =H50*$I$7 -> 350.262 | J50: =SUM(H50:I50) -> 2685.342
A51: 8.3.10 | B51: RL and topsoiling to PL01 - N1 | C51: £ | D51: =J51 -> 3853.3855 | H51: 3350.77 | I51: =H51*$I$7 -> 502.6155 | J51: =SUM(H51:I51) -> 3853.3855 | K51: LECI
A52: 8.3.11 | B52: RL and topsoiling to PL03 - N1 | C52: £ | D52: =J52 -> 7706.771 | H52: 6701.54 | I52: =H52*$I$7 -> 1005.231 | J52: =SUM(H52:I52) -> 7706.771 | K52: LECI
A53: 8.3.12 | B53: Extra for tree root protection - N1 | C53: £ | D53: =J53 -> 417.2775 | H53: 362.85 | I53: =H53*$I$7 -> 54.4275 | J53: =SUM(H53:I53) -> 417.2775 | K53: LECI
A54: 8.3.13 | B54: RL and topsoiling to PL04 - N1 | C54: £ | D54: =J54 -> 530.288 | H54: 461.12 | I54: =H54*$I$7 -> 69.168 | J54: =SUM(H54:I54) -> 530.288 | K54: LECI
A55: 8.3.14 | B55: RL and topsoiling to PL03 - N7 | C55: £ | D55: =J55 -> 3004.9385 | H55: 2612.99 | I55: =H55*$I$7 -> 391.9485 | J55: =SUM(H55:I55) -> 3004.9385 | K55: LECI
A56: 8.3.15 | B56: RL and topsoiling to PL04 - N7 | C56: £ | D56: =J56 -> 1343.384 | H56: 1168.16 | I56: =H56*$I$7 -> 175.224 | J56: =SUM(H56:I56) -> 1343.384 | K56: LECI
D57: =J57 -> 0
D58: =J58 -> 0
D59: =J59 -> 0
D60: =J60 -> 0 | I60: =H60*$I$7 -> 0 | J60: =SUM(H60:I60) -> 0
D61: =J61 -> 0 | I61: =H61*$I$7 -> 0 | J61: =SUM(H61:I61) -> 0
A62: 8.4 | B62: Fencing, Railings and Walls | C62: £ | D62: =J62 -> 0 | I62: =H62*$I$7 -> 0 | J62: =SUM(H62:I62) -> 0
A63: 8.4.1 | B63: Steel fencing 2.1m | C63: £ | D63: =J63 -> 0 | I63: =H63*$I$7 -> 0 | J63: =SUM(H63:I63) -> 0
A64: 8.4.2 | B64: Steel Gate - double fob access | C64: £ | D64: =J64 -> 0 | I64: =H64*$I$7 -> 0 | J64: =SUM(H64:I64) -> 0
A65: 8.4.3 | B65: Steel Gate - single fob access | C65: £ | D65: =J65 -> 4443.025 | H65: =3313.5+550 -> 3863.5 | I65: =H65*$I$7 -> 579.525 | J65: =SUM(H65:I65) -> 4443.025 | K65: Single leaf gates
A66: 8.4.4 | B66: Railing - 900mm | C66: £ | D66: =J66 -> 16171.404 | H66: 14062.09 | I66: =H66*$I$7 -> 2109.3135 | J66: =SUM(H66:I66) -> 16171.404
A67: 8.4.5 | B67: Timber fence repairs | C67: £ | D67: =J67 -> 0 | I67: =H67*$I$7 -> 0 | J67: =SUM(H67:I67) -> 0
A68: 8.4.6 | B68: Brick boundary wall - 900mm Protection guard rail - N1 | C68: £ | D68: =J68 -> 15180 | H68: =44*300 -> 13200 | I68: =H68*$I$7 -> 1980 | J68: =SUM(H68:I68) -> 15180
A69: 8.4.7 | B69: Brick boundary wall - 1100mm | C69: £ | D69: =J69 -> 6210 | H69: =18*300 -> 5400 | I69: =H69*$I$7 -> 810 | J69: =SUM(H69:I69) -> 6210
A70: 8.4.8 | B70: Railing to new play areas | C70: £ | D70: =J70 -> 0 | I70: =H70*$I$7 -> 0 | J70: =SUM(H70:I70) -> 0
A71: 8.4.9 | B71: Railing reuse existing play area | C71: £ | D71: =J71 -> 0 | I71: =H71*$I$7 -> 0 | J71: =SUM(H71:I71) -> 0
A72: 8.4.10 | B72: Muga Fence repairs | C72: £ | D72: =J72 -> 0 | I72: =H72*$I$7 -> 0 | J72: =SUM(H72:I72) -> 0
A73: 8.4.11 | B73: Gates to private terraces | C73: £ | D73: =J73 -> 0 | I73: =H73*$I$7 -> 0 | J73: =SUM(H73:I73) -> 0
A74: 8.4.12 | B74: Single gates | C74: £ | D74: =J74 -> 0 | I74: =H74*$I$7 -> 0 | J74: =SUM(H74:I74) -> 0 | K74: Single leaf gates
A75: 8.4.13 | B75: Foundations to brick / boundary walls - N1 | C75: £ | D75: =J75 -> 4493.7515 | H75: 3907.61 | I75: =H75*$I$7 -> 586.1415 | J75: =SUM(H75:I75) -> 4493.7515 | K75: LECI
A76: 8.4.14 | B76: Foundations to brick / boundary walls - N7 | C76: £ | D76: =J76 -> 1979.426 | H76: 1721.24 | I76: =H76*$I$7 -> 258.186 | J76: =SUM(H76:I76) -> 1979.426 | K76: LECI
D77: =J77 -> 0
A78: 8.5 | B78: External Fixtures | D78: =J78 -> 0 | I78: =H78*$I$7 -> 0 | J78: =SUM(H78:I78) -> 0
A79: 8.5.1 | B79: Cycle Racks | C79: £ | D79: =J79 -> 312.8 | H79: 272 | I79: =H79*$I$7 -> 40.8 | J79: =SUM(H79:I79) -> 312.8
A80: 8.5.2 | B80: Play Equipment | I80: =H80*$I$7 -> 0 | J80: =SUM(H80:I80) -> 0
A81: 8.5.2.1 | B81: NRO115: Kompan snail springer | C81: £ | D81: =J81 -> 3506.3098 | H81: =1250.32+(3597.29/2) -> 3048.965 | I81: =H81*$I$7 -> 457.34475 | J81: =SUM(H81:I81) -> 3506.3098
A82: 8.5.4 | B82: NRO118: Kompan bee springer | C82: £ | D82: =J82 -> 3506.3098 | H82: =1250.32+(3597.29/2) -> 3048.965 | I82: =H82*$I$7 -> 457.34475 | J82: =SUM(H82:I82) -> 3506.3098
A83: 8.5.5 | B83: NRO906: Kompan bird nest swing | C83: £ | D83: =J83 -> 4285.682 | H83: 3726.68 | I83: =H83*$I$7 -> 559.002 | J83: =SUM(H83:I83) -> 4285.682
A84: 8.5.6 | B84: PCM157: Kompan wheelchair carousel | C84: £ | D84: =J84 -> 5728.656 | H84: 4981.44 | I84: =H84*$I$7 -> 747.216 | J84: =SUM(H84:I84) -> 5728.656
A85: 8.5.7 | B85: NRC200201: Kompan spellbound shack | C85: £ | D85: =J85 -> 17310.72 | H85: 15052.8 | I85: =H85*$I$7 -> 2257.92 | J85: =SUM(H85:I85) -> 17310.72
A86: 8.5.8 | B86: NRO827: Kompan Balance Beam on Springs | C86: £ | D86: =J86 -> 1632.54 | H86: 1419.6 | I86: =H86*$I$7 -> 212.94 | J86: =SUM(H86:I86) -> 1632.54
A87: 8.5.9 | B87: NRO826: Kompan Crawling Pyramid | C87: £ | D87: =J87 -> 3284.4575 | H87: 2856.05 | I87: =H87*$I$7 -> 428.4075 | J87: =SUM(H87:I87) -> 3284.4575
A88: 8.5.10 | B88: NRO813: Kompan Climbing Net | C88: £ | D88: =J88 -> 5179.094 | H88: 4503.56 | I88: =H88*$I$7 -> 675.534 | J88: =SUM(H88:I88) -> 5179.094
A89: 8.5.11 | B89: NRO810: Kompan Wobble Bridge | C89: £ | D89: =J89 -> 4806.632 | H89: 4179.68 | I89: =H89*$I$7 -> 626.952 | J89: =SUM(H89:I89) -> 4806.632
A90: 8.5.12 | B90: Large litter bins | C90: £ | D90: =J90 -> 0 | I90: =H90*$I$7 -> 0 | J90: =SUM(H90:I90) -> 0
A91: 8.5.13 | B91: Bat boxes | C91: £ | D91: =J91 -> 684.02 | H91: 594.8 | I91: =H91*$I$7 -> 89.22 | J91: =SUM(H91:I91) -> 684.02
A92: 8.5.14 | B92: Bird nest boxes | C92: £ | D92: =J92 -> 111.826 | H92: 97.24 | I92: =H92*$I$7 -> 14.586 | J92: =SUM(H92:I92) -> 111.826
A93: 8.5.15 | B93: Insect nest boxes | C93: £ | D93: =J93 -> 487.462 | H93: 423.88 | I93: =H93*$I$7 -> 63.582 | J93: =SUM(H93:I93) -> 487.462
A94: 8.5.16 | B94: Other site, street furniture and equipment: | C94: £ | D94: =J94 -> 0 | I94: =H94*$I$7 -> 0 | J94: =SUM(H94:I94) -> 0
B95: Site Handover and signage | C95: £ | D95: =J95 -> 1039.6 | H95: =584+320 -> 904 | I95: =H95*$I$7 -> 135.6 | J95: =SUM(H95:I95) -> 1039.6
I96: =H96*$I$7 -> 0 | J96: =SUM(H96:I96) -> 0
I97: =H97*$I$7 -> 0 | J97: =SUM(H97:I97) -> 0
I98: =H98*$I$7 -> 0 | J98: =SUM(H98:I98) -> 0
A100: 8.6 | B100: External Drainage | I100: =H100*$I$7 -> 0 | J100: =SUM(H100:I100) -> 0
A101: 8.6.2 | B101: N1 storm water drainage | I101: =H101*$I$7 -> 0 | J101: =SUM(H101:I101) -> 0
A102: 8.6.3 | B102: Excavate for pipe | C102: £ | D102: =J102 -> 3370.4085 | H102: 2930.79 | I102: =H102*$I$7 -> 439.6185 | J102: =SUM(H102:I102) -> 3370.4085 | K102: LECI
A103: 8.6.4 | B103: Bed and surround | C103: £ | D103: =J103 -> 2264.741 | H103: 1969.34 | I103: =H103*$I$7 -> 295.401 | J103: =SUM(H103:I103) -> 2264.741 | K103: LECI
A104: 8.6.5 | B104: Pipework | C104: £ | D104: =J104 -> 4505.5045 | H104: 3917.83 | I104: =H104*$I$7 -> 587.6745 | J104: =SUM(H104:I104) -> 4505.5045 | K104: LECI
A105: 8.6.6 | B105: Slot drain | C105: £ | D105: =J105 -> 1554.8 | H105: 1352 | I105: =H105*$I$7 -> 202.8 | J105: =SUM(H105:I105) -> 1554.8 | K105: LECI
...

Sheet E-Contractor's Proposals
A1: E - Cost Breakdown - Contractor's Proposals
A3: Ref | B3: Element | D3: Total
A5: F | B5: CONTRACTOR'S PROPOSALS
B7: The Contractor is to list below:-
A9: 1 | B9: Any other costs attributable to any items of work not specifically identified within the Contract Sum Analysis but included by the Contractor in his tender
A13: 2 | B13: Any items included by the Contractor which are in addition to or deviate from the Employer's Requirements
B17: Please provide breakdown itemised items below (to be insert by the contractor):
C20: £ | D20: =SUM(C20:C20) -> 0
C22: £ | D22: =SUM(C22:C22) -> 0
C24: £ | D24: =SUM(C24:C24) -> 0
C26: £ | D26: =SUM(C26:C26) -> 0
C28: £ | D28: =SUM(C28:C28) -> 0
C30: £ | D30: =SUM(C30:C30) -> 0
C32: £ | D32: =SUM(C32:C32) -> 0
C34: £ | D34: =SUM(C34:C34) -> 0
C36: £ | D36: =SUM(C36:C36) -> 0
B66: Carried To Summary | C66: £ | D66: =SUM(D4:D65) -> 0

Sheet F-Works outside the boundary
A1: F - Cost Breakdown - Works outside the boundary of the site
A3: Ref | B3: Element | D3: Total | H3: Cost | I3: 0.15 | J3: Rate to be used
A5: F | B5: WORKS OUTSIDE THE BOUNDARY OF THE SITE
B7: Please refer to the following tender documents for guidelines on pricing:
B9: The Contractor is to list below:-
B11: New cycle bases around the development | C11: £ | D11: =J11 -> 33109.88 | H11: 28791.2 | I11: =H11*$I$3 -> 4318.68 | J11: =SUM(H11:I11) -> 33109.88
I12: =H12*$I$3 -> 0 | J12: =SUM(H12:I12) -> 0
B13: New cycle storage units | C13: £ | D13: =J13 -> 166750 | H13: 145000 | I13: =H13*$I$3 -> 21750 | J13: =SUM(H13:I13) -> 166750
I14: =H14*$I$3 -> 0 | J14: =SUM(H14:I14) -> 0
B15: Wall to be rebuilt | C15: £ | D15: =J15 -> 2300 | H15: 2000 | I15: =H15*$I$3 -> 300 | J15: =SUM(H15:I15) -> 2300
I16: =H16*$I$3 -> 0 | J16: =SUM(H16:I16) -> 0
B17: White lining | C17: £ | D17: =J17 -> 1552.5 | H17: 1350 | I17: =H17*$I$3 -> 202.5 | J17: =SUM(H17:I17) -> 1552.5
I18: =H18*$I$3 -> 0 | J18: =SUM(H18:I18) -> 0
B19: Hardlandscaping to be lifted and replaced with soft landscaping | C19: £ | D19: =J19 -> 2809.128 | H19: 2442.72 | I19: =H19*$I$3 -> 366.408 | J19: =SUM(H19:I19) -> 2809.128
B46: Carried To Summary | C46: £ | D46: =SUM(D4:D45) -> 206521.51

Sheet G-Aftercare
A1: G - Cost Breakdown - Aftercare
A3: Ref | B3: Element | D3: Total
A5: H | B5: AFTERCARE - 24 MONTHS DEFECTS
A7: 1 | B7: General | C7: £ | D7: =SUM(C7:C7) -> 0
A9: 2 | B9: Soft Landscaping | C9: £
A11: 3 | B11: Green & Brown roofs | C11: £ | D11: =SUM(C11:C11) -> 0
A13: 4 | B13: Roof access & mansafe systems | C13: £ | D13: =SUM(C13:C13) -> 0
A15: 5 | B15: Lifts | C15: £ | D15: =SUM(C15:C15) -> 0
A17: 6 | B17: M+E | C17: £ | D17: =SUM(C17:C17) -> 0
A19: 7 | B19: Plant Equipment | C19: £ | D19: =SUM(C19:C19) -> 0
A21: 8 | B21: Water storage & Booster Tanks | C21: £ | D21: =SUM(C21:C21) -> 0
A23: 9 | B23: IRS System | C23: £ | D23: =SUM(C23:C23) -> 0
A25: 10 | B25: PVs | C25: £ | D25: =SUM(C25:C25) -> 0
A27: 11 | B27: ASHPs | C27: £ | D27: =SUM(C27:C27) -> 0
A29: 12 | B29: AOVs | C29: £ | D29: =SUM(C29:C29) -> 0
A31: 13 | B31: Fire Alarm System | C31: £ | D31: =SUM(C31:C31) -> 0
A33: 14 | B33: Door Entry System | C33: £ | D33: =SUM(C33:C33) -> 0
... A37: 16 | B37: Out of Hours Emergency Defects Team | C37: £ | D37: =SUM(C37:C37) -> 0
A39: 17 | B39: Please list below any other items that the contractor deems necessary:
C41: £ | D41: =SUM(C41:C41) -> 0
C43: £ | D43: =SUM(C43:C43) -> 0
C45: £ | D45: =SUM(C45:C45) -> 0
C47: £ | D47: =SUM(C47:C47) -> 0
C49: £ | D49: =SUM(C49:C49) -> 0
C51: £ | D51: =SUM(C51:C51) -> 0
C53: £ | D53: =SUM(C53:C53) -> 0
C55: £ | D55: =SUM(C55:C55) -> 0
C57: £ | D57: =SUM(C57:C57) -> 0
C59: £ | D59: =SUM(C59:C59) -> 0
B62: Carried To Summary | C62: £ | D62: =SUM(D5:D60) -> 0

Sheet L-Alternative Costs
A1: M - Alternative Costs
A3: Ref | B3: Element | D3: Total
J4: 10.76
B5: Please provide your cost proposals for the alternative items below: | I5: =491.97-82.23 -> 409.74 | J5: =I5*J4 -> 4408.8024 | K5: 689787 | L5: =K5/J5 -> 156.45677
I6: 192.06 | J6: =I6*J4 -> 2066.5656 | K6: 194104 | L6: =K6/J6 -> 93.925884
A7: 1 | B7: Parent Company Guarantee (PCG) | C7: £ | D7: =SUM(C7:C7) -> 0 | L7: =L5-L6 -> 62.53089
A9: 2 | C9: £ | D9: =SUM(C9:C9) -> 0
A11: 3 | C11: £ | D11: =SUM(C11:C11) -> 0
A13: 4 | C13: £ | D13: =SUM(C13:C13) -> 0
A15: 5 | C15: £ | D15: =SUM(C15:C15) -> 0
A17: 6 | C17: £ | D17: =SUM(C17:C17) -> 0
A19: 7 | C19: £ | D19: =SUM(C19:C19) -> 0
B49: Carried To Summary | C49: £ | D49: =SUM(D4:D48) -> 0
