Workbook

Sheet Summary
A2: ='02 Plot Groundworks'!A2 -> The Former Police Station, Haslingden | C2: SUMMARY
B6: SUMMARY | C6: Page Nr | D6: Total
D7: £
B9: SECTION 1 - PRELIMINARIES | D9: ='01 Prelims'!E63 -> 352400
B11: SECTION 2 - PLOT GROUNDWORKS | D11: ='02 Plot Groundworks'!F39 -> 14410.65
B13: SECTION 3 - EXTERNAL GROUNDWORKS | D13: =SUM('03 External Groundworks'!F270,'03 External Groundworks'!F200,'03 External Groundworks'!F129,'03 External Groundworks'!F49) -> 159217.9
B15: SECTION 4 - EXTERNAL FAÇADE | D15: =SUM('04 External Facade'!F59,'04 External Facade'!F92) -> 132676.43
B17: SECTION 5 - DRYLINING, SCREED & RENDER | D17: =SUM('05 Drylining, Screed & Render'!F44,'05 Drylining, Screed & Render'!F74,'05 Drylining, Screed & Render'!F115,'05 Drylining, Screed & Render'!F146) -> 140587.78
B19: SECTION 6 - M&E | D19: =SUM('06 M&E'!F38) -> 168400
B21: SECTION 7 - CARPENTRY | D21: =SUM('07 Carpentry'!F45,'07 Carpentry'!F81,'07 Carpentry'!F118,'07 Carpentry'!F161,'07 Carpentry'!F197,'07 Carpentry'!F234) -> 49353.92
B23: SECTION 8 - ROOF COVERINGS | D23: =SUM('08 Roof Coverings'!F38) -> 67381.943
B25: SECTION 9 - DECORATING AND OTHER FINISHINGS | D25: =SUM('09 Decorating & Other Finishing'!F57,'09 Decorating & Other Finishing'!F97) -> 199797.8
B27: SECTION 10 - MATERIALS | D27: =SUM('10 Materials'!F66,'10 Materials'!F130) -> 267184.45
B29: SECTION 11 - LANDSCAPING | D29: =SUM('11 Landscaping'!F64) -> 8344
B31: SECTION 12 - WALLS & FENCES | D31: =SUM('12 Walls & Fences'!F64) -> 41894
B33: Sub total | D33: =SUM(D9:D32) -> 1601648.9
B35: Add overheads and profit | C35: 0.15 | D35: =D33*C35 -> 240247.33
B37: Total Sqft | C37: =SUM('09 Decorating & Other Finishing'!C10,'09 Decorating & Other Finishing'!C14) -> 10142
B39: Build cost per sqft (Plot works only) | C39: =SUM(D11,D15,D17,D19,D21,D23,D25,D27,'01 Prelims'!E45)/C37 -> 109.22826
B41: Entire site cost per sqft | C41: =SUM(D9:D31)/C37 -> 157.92239
B46: CARRIED TO FORM OF TENDER | C46: £ | D46: =SUM(D33:D44) -> 1841896.2

Sheet 00 General Clarifications
B2: General Assumptions & Clarifications (to be read in conjunction with those within each tab of the work schedule)
B4: Ref. | C4: General Assumption/Clarification
C5: These assumptions & clarifications are to be read in conjunction with those within each tab of the work schedule
C6: We note the site is served by power, water and telecoms and assume we will be able to connect to these services and have beneficial use during the works
C7: We have made no allowances for taking control of any statutory authority quotations for utilites on or off site.
C8: Any on site material will need to be WAC tested before dispoal from site, this can be arranged by the contractor for an additional fee.
C9: Full soil investigation information will need to be provided to the contractor before the cost for cart away can be established - all cart away assumed Inert
C10: We have assumed that any potential habitat/ecology issues, such as bats, badgers, tree protection, etc., will not have a detrimental effect on programme
C11: We have made no allowance for any making good of the highway, surfaces, verges, fencing, etc., leading to site, and do not accept any responsibility for any damage caused during the progress of the works
C12: We agree the use of JCT ICD 2016 unamended (except for retention to be at 3%) is appropriate for this project
C13: We have forecast a programme period of 48 weeks on site
C14: We will require the early payment of any supplier deposits/stage payments, etc., as per their terms to ensure the smooth running of the project. We will try to time these payments to suit valuation dates, but in some instances it may require an interim payment. We are happy to investigate Vesting as required
C15: We have assumed that all information supplied for pricing purposes is accurate, and we have the right to additional time and/or costs if the tender information is proven to be insufficient or cannot be relied upon
C16: We have assumed that all directly employed/nominated suppliers can meet the dates required within our programme, and any delay caused or due to any directly employed/nominated suppliers will be subject to additional time and/or cost
... C25: We have assumed vacant possession and uninterrupted access to the site at all times

Sheet 01 Prelims
A2: =Summary!A2 -> The Former Police Station, Haslingden | D2: PRELIMINARIES
A4: Description | B4: Quantity | C4: Unit | D4: Rate | E4: £
A5: Contract period | B5: 48 | C5: wks
A7: Supervision & Labour
A8: Contracts Manager (1.5 day/week) | B8: 44 | C8: wks | D8: 750 | E8: =ROUND(B8 * D8,2) -> 33000
A9: Site Manager | B9: =$B$5 -> 48 | C9: wks | D9: 1750 | E9: =ROUND(B9 * D9,2) -> 84000
A10: Quantity Surveyor (1.5 day/week) | B10: =$B$5 -> 48 | C10: wks | D10: 750 | E10: =ROUND(B10 * D10,2) -> 36000
A11: Temporary Works Design - done by Structural engineer | B11: 1 | C11: PS | D11: 0 | E11: =ROUND(B11 * D11,2) -> 0
A12: Labourer | B12: =$B$5 -> 48 | C12: wks | D12: 500 | E12: =ROUND(B12 * D12,2) -> 24000
A13: Forklift Driver | B13: 40 | C13: wks | D13: 880 | E13: =ROUND(B13 * D13,2) -> 35200
A14: Setting out | B14: 2 | C14: wks | D14: 1500 | E14: =ROUND(B14 * D14,2) -> 3000
A16: Site Offices, Compound & Security
A17: Formation of site office and welfare area in basement including dismantling when works to basement due to commence | B17: 1 | C17: item | D17: 2220 | E17: =ROUND(B17 * D17,2) -> 2220
A18: Formation of site office and welfare area in basement including dismantling when works to basement due to commence | C18: wks | E18: Excluded
A19: Site office/meeting room & steps | B19: 48 | C19: wks | D19: 55 | E19: =ROUND(B19 * D19,2) -> 2640
A20: Welfare unit | B20: 48 | C20: wks | D20: 50 | E20: =ROUND(B20 * D20,2) -> 2400
A21: Container | B21: 48 | C21: wks | D21: 20 | E21: =ROUND(B21 * D21,2) -> 960
A22: Site toilet | B22: 48 | C22: wks | D22: 30 | E22: =ROUND(B22 * D22,2) -> 1440
A23: Delivery and collection of all site offices, welfare unit, toilets and container | B23: 1 | C23: item | D23: 1580 | E23: =ROUND(B23 * D23,2) -> 1580
A24: Connect site offices and welfare to power and water | B24: 1 | C24: item | D24: 1500 | E24: =ROUND(B24 * D24,2) -> 1500
A25: IT equipment, printing, etc. | B25: =$B$5 -> 48 | C25: wks | D25: 35 | E25: =ROUND(B25 * D25,2) -> 1680
A26: Welfare equipment/tea & coffee, etc. | B26: =$B$5 -> 48 | C26: wks | D26: 15 | E26: =ROUND(B26 * D26,2) -> 720
A27: Security | C27: wks | E27: Excluded
A28: Temp. fencing & barriers | B28: 1 | C28: item | D28: 500 | E28: =ROUND(B28 * D28,2) -> 500
A29: Hardstanding for laydown, turning areas, maintain and reinstate | C29: item | E29: Excluded
A31: Temporary Site Services
A32: Supply & install lighting/power | B32: 1 | C32: item | D32: 2400 | E32: =ROUND(B32 * D32,2) -> 2400
A33: Telephone and internet | B33: =$B$5 -> 48 | C33: wks | D33: 35 | E33: =ROUND(B33 * D33,2) -> 1680
A34: Water connection and supply | B34: 1 | C34: item | D34: 600 | E34: =ROUND(B34 * D34,2) -> 600
A35: Temporary heating and drying | B35: 1 | C35: item | D35: 1500 | E35: =ROUND(B35 * D35,2) -> 1500
A37: Plant, Tools & Equipment
A38: Small Tools | B38: =$B$5 -> 48 | C38: wks | D38: 40 | E38: =ROUND(B38 * D38,2) -> 1920
A39: Forklift hire | B39: =B13 -> 40 | C39: wks | D39: 315 | E39: =ROUND(B39 * D39,2) -> 12600
A41: Scaffolding and Access Equipment
A42: Scaffolding to Compound | B42: 1 | C42: PS | D42: 3500 | E42: =ROUND(B42 * D42,2) -> 3500
A43: Allowance for adaptations | B43: 1 | C43: PS | D43: 0 | E43: =ROUND(B43 * D43,2) -> 0
A44: Alloy towers, hop-ups, trestles & specialist internal access | B44: 1 | C44: item | D44: 1000 | E44: =ROUND(B44 * D44,2) -> 1000
A45: Scaffolding to plots | B45: 8 | C45: plots | D45: 8500 | E45: =ROUND(B45 * D45,2) -> 68000
A47: Clearance & Cleaning
A48: Clear rubbish from site - 12 yard skips | B48: =4*8 -> 32 | C48: nr | D48: 375 | E48: =ROUND(B48 * D48,2) -> 12000
A49: Temporary protection | B49: 1 | C49: item | D49: 2000 | E49: =ROUND(B49 * D49,2) -> 2000
A50: Final contractors site clean (builders clean & sparkle clean) | B50: 1 | C50: item | D50: 1800 | E50: =ROUND(B50 * D50,2) -> 1800
A51: External window clean | B51: 1 | C51: item | D51: 500 | E51: =ROUND(B51 * D51,2) -> 500
A53: Sundries & Safety
A54: Health & Safety site set up, signs etc | B54: 1 | C54: item | D54: 1500 | E54: =ROUND(B54 * D54,2) -> 1500
A55: Health & safety - site inspections | B55: 1 | C55: item | D55: 1440 | E55: =ROUND(B55 * D55,2) -> 1440
A56: Fire Risk Management Plan, fire points, etc. | B56: 1 | C56: item | D56: 1600 | E56: =ROUND(B56 * D56,2) -> 1600
A57: O&M/Building Manual | B57: 1 | C57: item | D57: 2000 | E57: =ROUND(B57 * D57,2) -> 2000
A58: PPE | B58: 1 | C58: item | D58: 500 | E58: =ROUND(B58 * D58,2) -> 500
A60: Insurances
A61: Insurances | B61: 1 | C61: item | D61: 5020 | E61: =ROUND(B61 * D61,2) -> 5020
D63: Total | E63: =SUM(E8:E62) -> 352400
A65: Cost per week | E65: =E63/B5 -> 7341.6667
A66: Cost per month | D66: =48/4.33 -> 11.08545 | E66: =E63/D66 -> 31789.417

Sheet 02 Plot Groundworks
A2: The Former Police Station, Haslingden | D2: PLOT GROUNDWORKS | F2: SECTION 2 | G2: Comments
B4: Description | C4: Quantity | D4: Unit | E4: Rate | F4: Total
B6: Plot Groundworks | F6: =IF(C6="","",(C6*E6))
B8: Block B
F9: =IF(C9="","",(C9*E9))
A10: A | B10: Supply & installation of 150mm block & beam flooring to semi detatched unit (Block B) | C10: 89 | D10: m2 | E10: 65 | F10: =IF(C10="","",(C10*E10)) -> 5785
A12: B | B12: Domestic services to block B | C12: 2 | D12: no | E12: 300 | F12: =IF(C12="","",(C12*E12)) -> 600
A14: C | B14: Facing bricks to DPC (Bradstone) supply and lay | C14: =40*0.45 -> 18 | D14: m2 | E14: 104.25 | F14: =IF(C14="","",(C14*E14)) -> 1876.5
A16: D | B16: Telescopic vents and air bricks | C16: =40/2 -> 20 | D16: no | E16: 9.88 | F16: =IF(C16="","",(C16*E16)) -> 197.6
A18: E | B18: Concrete cavity fill | C18: =47*0.125*0.3 -> 1.7625 | D18: m3 | E18: 256 | F18: =IF(C18="","",(C18*E18)) -> 451.2
A20: F | B20: Supply and lay blockwork to support screed | C20: =54*0.225 -> 12.15 | D20: m2 | E20: 49.2 | F20: =IF(C20="","",(C20*E20)) -> 597.78
B22: Block A
A24: G | B24: Supply & installation of 150mm block & beam flooring to semi detatched unit (Block A) | D24: m2 | F24: Excluded
A26: H | B26: Domestic services to block A | C26: 6 | D26: no | E26: 300 | F26: =IF(C26="","",(C26*E26)) -> 1800
A28: I | B28: Facing bricks to DPC (Bradstone) | D28: m2 | F28: Excluded
A30: J | B30: Telescopic vents and air bricks | D30: no | F30: Excluded
A32: K | B32: Concrete cavity fill | C32: =126*0.125*0.3 -> 4.725 | D32: m3 | E32: 256 | F32: =IF(C32="","",(C32*E32)) -> 1209.6
A34: L | B34: Supply and lay blockwork to support screed | C34: =171*0.225 -> 38.475 | D34: m2 | E34: 49.2 | F34: =IF(C34="","",(C34*E34)) -> 1892.97
D39: To collection | E39: £ | F39: =SUM(F5:F38) -> 14410.65
F44: =IF(C44="","",(C44*E44))
F46: =IF(C46="","",(C46*E46))
F48: =IF(C48="","",(C48*E48))
F50: =IF(C50="","",(C50*E50))
F52: =IF(C52="","",(C52*E52))
F54: =IF(C54="","",(C54*E54))
F56: =IF(C56="","",(C56*E56))
F58: =IF(C58="","",(C58*E58))
F61: =IF(C61="","",(C61*E61))
F62: =IF(C62="","",(C62*E62))
F64: =IF(C64="","",(C64*E64))
F65: =IF(C65="","",(C65*E65))
... F84: =IF(C84="","",(C84*E84))
D87: To collection | E87: £ | F87: =SUM(F44:F86) -> 0
B93: Collection
B95: Page 2/1 | F95: =F39 -> 14410.65
B97: Page 2/2 | F97: =F87 -> 0
F111: =IF(C111="","",(C111*E111))
E112: To Main Summary £ | F112: =SUM(F93:F111) -> 14410.65

Sheet 03 External Groundworks
A2: ='02 Plot Groundworks'!A2 -> The Former Police Station, Haslingden | D2: EXTERNAL GROUNDWORKS | F2: SECTION 3
B4: Description | C4: Quantity | D4: Unit | E4: Rate | F4: Total | G4: Comments
B6: Off site works
B8: Footpath Crossover detail - Manchester road | G8: Actual extent of surfacing required unknown, assumptions made. M2 is provisinal and subject to remeasure upon confirmation. Assumed local authority will not allow patching of tarmac to new kerb line.
A10: A | B10: Existing footway to be excavated and arisings removed from site to accommodate new kerb lines. Assumed depth of 500mm. | C10: =62*0.48 -> 29.76 | D10: m3 | E10: =(68+6.2)*1.2 -> 89.04 | F10: =IF(C10="","",(C10*E10)) -> 2649.8304 | G10: Assumed contaminated cart away, however SI would need to be reviewed in order to sure up costs. | I10: =800/12 -> 66.666667
F11: =IF(C11="","",(C11*E11))
A12: B | B12: Grade, shape and level | C12: 62 | D12: m2 | E12: 1.5 | F12: =IF(C12="","",(C12*E12)) -> 93
F13: =IF(C13="","",(C13*E13))
A14: C | B14: 300mm subbase type 1 stone | C14: =62*0.3 -> 18.6 | D14: m3 | E14: 64 | F14: =IF(C14="","",(C14*E14)) -> 1190.4
F15: =IF(C15="","",(C15*E15))
A16: D | B16: 70mm base course - material 20mm DBM road base | C16: 62 | D16: m2 | E16: 35 | F16: =IF(C16="","",(C16*E16)) -> 2170
F17: =IF(C17="","",(C17*E17))
A18: E | B18: 70mm binder course - material AC20 dense bin binder grade 100/150 | C18: 62 | D18: m2 | E18: 34 | F18: =IF(C18="","",(C18*E18)) -> 2108
F19: =IF(C19="","",(C19*E19))
A20: F | B20: Sweep tack & coat | C20: 62 | D20: m2 | E20: 2 | F20: =IF(C20="","",(C20*E20)) -> 124
F21: =IF(C21="","",(C21*E21))
A22: G | B22: 40mm wearing course - material SMF 10 surf binder grade 40/60 or PMB | C22: 62 | D22: m2 | E22: 31 | F22: =IF(C22="","",(C22*E22)) -> 1922
F23: =IF(C23="","",(C23*E23))
A24: H | B24: New radius kerb line required, 125mm upstand | C24: 12 | D24: m | E24: 32.5 | F24: =IF(C24="","",(C24*E24)) -> 390
F25: =IF(C25="","",(C25*E25))
A26: I | B26: Tactile paving required to crossing point | C26: 4 | D26: m2 | E26: 180 | F26: =IF(C26="","",(C26*E26)) -> 720
F27: =IF(C27="","",(C27*E27))
A28: J | B28: White lining | C28: 1 | D28: item | E28: 1000 | F28: =IF(C28="","",(C28*E28)) -> 1000 | G28: Provisional Sum
F29: =IF(C29="","",(C29*E29))
B30: Footpath Crossover detail - Hazeldene Avenue | F30: =IF(C30="","",(C30*E30)) | G30: Actual extent of surfacing required unknown, assumptions made. M2 is provisinal and subject to remeasure upon confirmation. Assumed local authority will not allow patching of tarmac to new kerb line.
F31: =IF(C31="","",(C31*E31))
A32: K | B32: Removal of exisitng kerbline and footpath to tie in revised makeup, removal off site. | C32: =22*0.48 -> 10.56 | D32: m3 | E32: =(68+6.2)*1.2 -> 89.04 | F32: =IF(C32="","",(C32*E32)) -> 940.2624
F33: =IF(C33="","",(C33*E33))
A34: L | B34: Grade, shape and level | C34: 22 | D34: m2 | E34: 1.5 | F34: =IF(C34="","",(C34*E34)) -> 33
F35: =IF(C35="","",(C35*E35))
A36: M | B36: 300mm subbase type 1 stone | C36: =22*0.3 -> 6.6 | D36: m3 | E36: 64 | F36: =IF(C36="","",(C36*E36)) -> 422.4
F37: =IF(C37="","",(C37*E37))
A38: N | B38: 70mm base course - material 20mm DBM road base | C38: 22 | D38: m2 | E38: 35 | F38: =IF(C38="","",(C38*E38)) -> 770
F39: =IF(C39="","",(C39*E39))
A40: O | B40: 70mm binder course - material AC20 dense bin binder grade 100/150 | C40: 22 | D40: m2 | E40: 34 | F40: =IF(C40="","",(C40*E40)) -> 748
F41: =IF(C41="","",(C41*E41))
A42: P | B42: Sweep tack & coat | C42: 22 | D42: m2 | E42: 2 | F42: =IF(C42="","",(C42*E42)) -> 44
F43: =IF(C43="","",(C43*E43))
A44: Q | B44: 40mm wearing course - material SMF 10 surf binder grade 40/60 or PMB | C44: 22 | D44: m2 | E44: 31 | F44: =IF(C44="","",(C44*E44)) -> 682
F45: =IF(C45="","",(C45*E45))
A46: R | B46: New straight kerb line required, 125mm upstand | C46: 9 | D46: m | E46: 32.5 | F46: =IF(C46="","",(C46*E46)) -> 292.5
D49: To collection | E49: £ | F49: =SUM(F5:F46) -> 16299.393
B52: Collection
B54: Carpark
B56: Tarmac with green chippings | F56: =IF(C56="","",(C56*E56))
F57: =IF(C57="","",(C57*E57))
A58: S | B58: Excavate to reduced levels, cart off site for disposal. Bulking factor assumed at 1.3 | C58: =(193*0.24)*1.3 -> 60.216 | D58: m3 | E58: =(68+6.2)*1.2 -> 89.04 | F58: =IF(C58="","",(C58*E58)) -> 5361.6326 | G58: With limited proposed and existing level info this is made as an assumption at this stage. To be remeasured at a later stage.
A60: T | B60: Grade, shape and level | C60: 193 | D60: m2 | E60: 1.5 | F60: =IF(C60="","",(C60*E60)) -> 289.5
F61: =IF(C61="","",(C61*E61))
A62: U | B62: Terram | C62: 193 | D62: m2 | E62: 1.75 | F62: =IF(C62="","",(C62*E62)) -> 337.75
F63: =IF(C63="","",(C63*E63))
A64: V | B64: Well consolidated hardcore 150mm thick | C64: =193*0.15 -> 28.95 | D64: m3 | E64: 44 | F64: =IF(C64="","",(C64*E64)) -> 1273.8
F65: =IF(C65="","",(C65*E65))
A66: W | B66: 100mm dense macadam base course | C66: 193 | D66: m2 | E66: 50 | F66: =IF(C66="","",(C66*E66)) -> 9650
F67: =IF(C67="","",(C67*E67))
A68: X | B68: Sweep tack & coat | C68: 193 | D68: m2 | E68: 2 | F68: =IF(C68="","",(C68*E68)) -> 386
F69: =IF(C69="","",(C69*E69))
A70: Y | B70: 30mm stone mastic asphalt wearing course, 10mm size (green chippings) - including 60mm binder course | C70: 193 | D70: m2 | E70: 44 | F70: =IF(C70="","",(C70*E70)) -> 8492
F71: =IF(C71="","",(C71*E71))
A72: Z | B72: White lining | C72: 1 | D72: item | E72: 1000 | F72: =IF(C72="","",(C72*E72)) -> 1000 | G72: Provisional Sum
F73: =IF(C73="","",(C73*E73))
B74: Tarmac with red chippings | F74: =IF(C74="","",(C74*E74))
F75: =IF(C75="","",(C75*E75))
A76: AA | B76: Excavate to reduced levels, cart off site for disposal. Bulking factor assumed at 1.3 | C76: =(181*0.24)*1.3 -> 56.472 | D76: m3 | E76: =(68+6.2)*1.2 -> 89.04 | F76: =IF(C76="","",(C76*E76)) -> 5028.2669 | G76: With limited proposed and existing level info this is made as an assumption at this stage. To be remeasured at a later stage.
A78: AB | B78: Grade, shape and level | C78: 181 | D78: m2 | E78: 1.5 | F78: =IF(C78="","",(C78*E78)) -> 271.5
F79: =IF(C79="","",(C79*E79))
A80: AC | B80: Terram | C80: 181 | D80: m2 | E80: 1.75 | F80: =IF(C80="","",(C80*E80)) -> 316.75
F81: =IF(C81="","",(C81*E81))
A82: AD | B82: Well consolidated hardcore 150mm thick | C82: =181*0.15 -> 27.15 | D82: m3 | E82: 44 | F82: =IF(C82="","",(C82*E82)) -> 1194.6
F83: =IF(C83="","",(C83*E83))
A84: AE | B84: 100mm dense macadam base course | C84: 181 | D84: m2 | E84: 50 | F84: =IF(C84="","",(C84*E84)) -> 9050
F85: =IF(C85="","",(C85*E85))
A86: AF | B86: Sweep tack & coat | C86: =C84 -> 181 | D86: m2 | E86: 2 | F86: =IF(C86="","",(C86*E86)) -> 362
F87: =IF(C87="","",(C87*E87))
A88: AG | B88: 30mm stone mastic asphalt wearing course, 10mm size (red chippings) - including 60mm binder course | C88: 181 | D88: m2 | E88: 42 | F88: =IF(C88="","",(C88*E88)) -> 7602
F89: =IF(C89="","",(C89*E89))
A90: AH | B90: White lining | C90: 1 | D90: item | E90: 1000 | F90: =IF(C90="","",(C90*E90)) -> 1000 | G90: Provisional Sum
F91: =IF(C91="","",(C91*E91))
B92: Pedestrian Footpath | F92: =IF(C92="","",(C92*E92))
F93: =IF(C93="","",(C93*E93))
A94: AI | B94: Excavate to reduced levels, cart off site for disposal. Bulking factor assumed at 1.3 | C94: =(13*0.16)*1.3 -> 2.704 | D94: m3 | E94: =(68+6.2)*1.2 -> 89.04 | F94: =IF(C94="","",(C94*E94)) -> 240.76416 | G94: With limited proposed and existing level info this is made as an assumption at this stage. To be remeasured at a later stage.
F95: =IF(C95="","",(C95*E95))
A96: AJ | B96: Grade, shape and level | C96: 13 | D96: m2 | E96: 1.5 | F96: =IF(C96="","",(C96*E96)) -> 19.5
F97: =IF(C97="","",(C97*E97))
A98: AK | B98: Sub base 100mm thick type 1 | C98: =13*0.1 -> 1.3 | D98: m3 | E98: 64 | F98: =IF(C98="","",(C98*E98)) -> 83.2
F99: =IF(C99="","",(C99*E99))
A100: AL | B100: Base course - 40mm thick open graded macadam | C100: 13 | D100: m2 | E100: 24 | F100: =IF(C100="","",(C100*E100)) -> 312
F101: =IF(C101="","",(C101*E101))
A102: AM | B102: Sweep tack & coat | C102: 13 | D102: m2 | E102: 2 | F102: =IF(C102="","",(C102*E102)) -> 26
F103: =IF(C103="","",(C103*E103))
A104: AN | B104: wearing course - 20mm thick medium graded macadam | C104: 13 | D104: m2 | E104: 19 | F104: =IF(C104="","",(C104*E104)) -> 247
F105: =IF(C105="","",(C105*E105))
B106: Paving Slabs | F106: =IF(C106="","",(C106*E106))
F107: =IF(C107="","",(C107*E107))
A108: AO | B108: Excavate to reduced levels, cart off site for disposal. Bulking factor assumed at 1.3 | C108: =(173*0.2)*1.3 -> 44.98 | D108: m3 | E108: =(68+6.2)*1.2 -> 89.04 | F108: =IF(C108="","",(C108*E108)) -> 4005.0192 | G108: With limited proposed and existing level info this is made as an assumption at this stage. To be remeasured at a later stage.
A110: AP | B110: Grade, shape and level | C110: 173 | D110: m2 | E110: 1.5 | F110: =IF(C110="","",(C110*E110)) -> 259.5
F111: =IF(C111="","",(C111*E111))
A112: AQ | B112: 150mm hardcore bed | C112: =173*0.15 -> 25.95 | D112: m3 | E112: 44 | F112: =IF(C112="","",(C112*E112)) -> 1141.8
F113: =IF(C113="","",(C113*E113))
A114: AR | B114: 450 x 450mm Saxon paving slabs on continuous mortar bed | C114: 173 | D114: m2 | E114: 50 | F114: =IF(C114="","",(C114*E114)) -> 8650
...

Sheet 04 External Facade
A2: ='02 Plot Groundworks'!A2 -> The Former Police Station, Haslingden | D2: EXTERNAL FAÇADE | F2: SECTION 4
B4: Description | C4: Quantity | D4: Unit | E4: Rate | F4: Total | G4: Comments
B6: External Façade
B8: BLOCK A
A10: A | B10: Installation of radon DPC, lapped and taped to DPM | C10: 77 | D10: m | E10: 6.5 | F10: =IF(C10="","",(C10*E10)) -> 500.5
F11: =IF(C11="","",(C11*E11))
A12: B | B12: Installation of 100m bradstone or similar bed coursed artificial stone above DPC | C12: =326*1.1 -> 358.6 | D12: m2 | E12: 55 | F12: =IF(C12="","",(C12*E12)) -> 19723
A14: C | B14: Installation of 125mm cavity partially filled with 75mm Kingspan TW Thermawall cavity board | C14: =C16 -> 448 | D14: m2 | E14: 3.5 | F14: =IF(C14="","",(C14*E14)) -> 1568
A16: D | B16: Installation of 100mm concrete blockwork to inner leaf above DPC | C16: 448 | D16: m2 | E16: 22 | F16: =IF(C16="","",(C16*E16)) -> 9856
A18: E | B18: Installation of 100mm blockwork to internal walls | C18: =((15*2.5)*6)*1.1 -> 247.5 | D18: m2 | E18: 22 | F18: =IF(C18="","",(C18*E18)) -> 5445
A20: F | B20: Installation of 100mm concrete blocks to party wall including gable, lightweight aggregate blocks | C20: 838.1 | D20: m2 | E20: 22 | F20: =IF(C20="","",(C20*E20)) -> 18438.2
A22: G | B22: Installation of 100mm Isover RD Party Wall Insulation | C22: 419.01 | D22: m2 | E22: 3.5 | F22: =IF(C22="","",(C22*E22)) -> 1466.535
A24: H | B24: Installation of 100mm concrete blockwork to outer leaf to rendered sections including any bed joint reinforcement required | C24: =123*1.1 -> 135.3 | D24: m2 | E24: 22 | F24: =IF(C24="","",(C24*E24)) -> 2976.6
F25: =IF(C25="","",(C25*E25))
A26: I | B26: Installation of steel lintels | C26: =67+4 -> 71 | D26: m | E26: 19.5 | F26: =IF(C26="","",(C26*E26)) -> 1384.5
F27: =IF(C27="","",(C27*E27))
A28: J | B28: Installation of Ashlar stone heads and cills | C28: =46+59 -> 105 | D28: m | E28: 37.5 | F28: =IF(C28="","",(C28*E28)) -> 3937.5
F29: =IF(C29="","",(C29*E29))
A30: K | B30: DPC / Cavity trays required | C30: =C26 -> 71 | D30: m | E30: 6.5 | F30: =IF(C30="","",(C30*E30)) -> 461.5
F31: =IF(C31="","",(C31*E31))
A32: L | B32: Fixing of cavity formers | C32: 48 | D32: no | E32: 5 | F32: =IF(C32="","",(C32*E32)) -> 240
A34: M | B34: Jet wash / make good | C34: 6 | D34: no | E34: 225 | F34: =IF(C34="","",(C34*E34)) -> 1350
A36: N | B36: Service boxes | C36: 6 | D36: no | E36: 30 | F36: =IF(C36="","",(C36*E36)) -> 180
F37: =IF(C37="","",(C37*E37))
B38: BLOCK B | F38: =IF(C38="","",(C38*E38))
F39: =IF(C39="","",(C39*E39))
A40: O | B40: Installation of radon DPC, lapped and taped to DPM | C40: 40 | D40: m | E40: 6.5 | F40: =IF(C40="","",(C40*E40)) -> 260
F41: =IF(C41="","",(C41*E41))
A42: P | B42: Installation of 100m bradstone or similar bed coursed artificial stone above DPC | C42: =192*1.1 -> 211.2 | D42: m2 | E42: 55 | F42: =IF(C42="","",(C42*E42)) -> 11616
F43: =IF(C43="","",(C43*E43))
A44: Q | B44: Installation of 125mm cavity partially filled with 75mm Kingspan TW Thermawall cavity board | C44: =C46 -> 256.2 | D44: m2 | E44: 3.5 | F44: =IF(C44="","",(C44*E44)) -> 896.7
F45: =IF(C45="","",(C45*E45))
A46: R | B46: Installation of 100mm concrete blockwork to inner leaf above DPC | C46: =C52+C42 -> 256.2 | D46: m2 | E46: 22 | F46: =IF(C46="","",(C46*E46)) -> 5636.4
A48: S | B48: Installation of 100mm concrete blocks to party wall including gable, lightweight aggregate blocks | C48: 138 | D48: m2 | E48: 22 | F48: =IF(C48="","",(C48*E48)) -> 3036
F49: =IF(C49="","",(C49*E49))
A50: T | B50: Installation of 100mm Isover RD Party Wall Insulation | C50: 69 | D50: m2 | E50: 3.5 | F50: =IF(C50="","",(C50*E50)) -> 241.5
A52: U | B52: Installation of 100mm concrete blockwork to outer leaf to rendered sections including any bed joint reinforcement required | C52: 45 | D52: m2 | E52: 22 | F52: =IF(C52="","",(C52*E52)) -> 990
F53: =IF(C53="","",(C53*E53))
A54: V | B54: Installation of steel lintels | C54: =3+24+2 -> 29 | D54: m | E54: 19.5 | F54: =IF(C54="","",(C54*E54)) -> 565.5
F55: =IF(C55="","",(C55*E55))
A56: W | B56: Installation of Ashlar stone heads and cills | C56: =19+24 -> 43 | D56: m | E56: 37.5 | F56: =IF(C56="","",(C56*E56)) -> 1612.5
C59: To collection | F59: =SUM(F6:F58) -> 92381.935
F61: =IF(C61="","",(C61*E61))
B62: Collection
F63: =IF(C63="","",(C63*E63))
A64: X | B64: DPC / Cavity trays required | C64: =C54 -> 29 | D64: m | E64: 6.5 | F64: =IF(C64="","",(C64*E64)) -> 188.5
A66: Y | B66: Fixing of cavity formers | C66: 19 | D66: no | E66: 5 | F66: =IF(C66="","",(C66*E66)) -> 95
A68: Z | B68: Jet wash / make good | C68: 2 | D68: no | E68: 225 | F68: =IF(C68="","",(C68*E68)) -> 450
A70: AA | B70: Service boxes | C70: 2 | D70: no | E70: 30 | F70: =IF(C70="","",(C70*E70)) -> 60
B72: Windows - colour to be dark grey, supply and install
A74: AB | B74: Type A - 1507 x 797mm | C74: 31 | D74: no | E74: 481 | F74: =IF(C74="","",(C74*E74)) -> 14911 | H74: =1.507*0.797 -> 1.201079 | I74: 400 | J74: =H74*I74 -> 480.4316
A76: AC | B76: Type B - 1507 x 797mm w obscure glazing | C76: 2 | D76: no | E76: 481 | F76: =IF(C76="","",(C76*E76)) -> 962 | H76: =1.507*0.797 -> 1.201079 | I76: 400 | J76: =H76*I76 -> 480.4316
A78: AD | B78: Type C - 1347 x 797mm w obscure glazing | C78: 2 | D78: no | E78: 430 | F78: =IF(C78="","",(C78*E78)) -> 860 | H78: =1.347*0.797 -> 1.073559 | I78: 400 | J78: =H78*I78 -> 429.4236
A80: AE | B80: Type D - 1585 x 1360mm | C80: 8 | D80: no | E80: 863 | F80: =IF(C80="","",(C80*E80)) -> 6904 | H80: =1.585*1.36 -> 2.1556 | I80: 400 | J80: =H80*I80 -> 862.24
A82: AF | B82: Type E - 1023 x 1110mm | C82: 4 | D82: no | E82: 455 | F82: =IF(C82="","",(C82*E82)) -> 1820 | H82: =1.023*1.11 -> 1.13553 | I82: 400 | J82: =H82*I82 -> 454.212
A84: AG | B84: Type G - 1023 x 1110mm | C84: 4 | D84: no | E84: 455 | F84: =IF(C84="","",(C84*E84)) -> 1820 | H84: =1.023*1.11 -> 1.13553 | I84: 400 | J84: =H84*I84 -> 454.212
B86: Patio doors - colour to be dark grey, supply and install
A88: AH | B88: Type F - 1810 x 2110mm | C88: 8 | D88: no | E88: 1528 | F88: =IF(C88="","",(C88*E88)) -> 12224 | H88: =1.81*2.11 -> 3.8191 | I88: 400 | J88: =H88*I88 -> 1527.64
C92: To Main Summary £ | F92: =SUM(F61:F90) -> 40294.5

Sheet 05 Drylining, Screed & Render
A2: ='02 Plot Groundworks'!A2 -> The Former Police Station, Haslingden | D2: DRYLINING, SCREED | F2: SECTION 5
D3: RENDER
B4: Description | C4: Quantity | D4: Unit | E4: Rate | F4: Total | G4: Comments
B5: Block A
A7: A | B7: 75mm sand and cement screed laid on 150mm PIR Kingspan Thermafloor TF70 insulation, Gas Radon DPM. | C7: 256 | D7: m2 | E7: 55 | F7: =IF(C7="","",(C7*E7)) -> 14080
F8: =IF(C8="","",(C8*E8))
B9: Ceilings | F9: =IF(C9="","",(C9*E9))
F10: =IF(C10="","",(C10*E10))
A11: B | B11: 1no layer of 15mm wallboard | D11: m2 | F11: =IF(C11="","",(C11*E11))
F12: =IF(C12="","",(C12*E12))
A13: C | B13: 1no layer of 15mm fireline wallboard | C13: =((43*6)*2)+(29*4.49) -> 646.21 | D13: m2 | E13: 12.5 | F13: =IF(C13="","",(C13*E13)) -> 8077.625
F14: =IF(C14="","",(C14*E14))
A15: D | B15: Skeilings - 120mm Kooltherm K107, 82.5mm Kooltherm K118 Insulated Board | C15: =3.9*29 -> 113.1 | D15: m2 | E15: 70 | F15: =IF(C15="","",(C15*E15)) -> 7917
F16: =IF(C16="","",(C16*E16))
A17: E | B17: EO moisture board | C17: =(2.13+4.37+5.34)*6 -> 71.04 | D17: m2 | E17: 7.25 | F17: =IF(C17="","",(C17*E17)) -> 515.04
F18: =IF(C18="","",(C18*E18))
A19: F | B19: Eo tape & joint | C19: =C15+C13 -> 759.31 | D19: m2 | E19: 6 | F19: =IF(C19="","",(C19*E19)) -> 4555.86
A21: G | B21: EO Skim Finish | C21: =C15+C13 -> 759.31 | D21: m2 | E21: 7 | F21: =IF(C21="","",(C21*E21)) -> 5315.17
F22: =IF(C22="","",(C22*E22))
B23: Walls | F23: =IF(C23="","",(C23*E23))
F24: =IF(C24="","",(C24*E24))
A25: H | B25: Dot & dab external walls | C25: =((58*2.5)*6) -> 870 | D25: m2 | E25: 11.6 | F25: =IF(C25="","",(C25*E25)) -> 10092
F26: =IF(C26="","",(C26*E26))
A27: I | B27: Dot & dab internal blockwork walls | C27: =(29*2.5)*6 -> 435 | D27: m2 | E27: 11.6 | F27: =IF(C27="","",(C27*E27)) -> 5046
F28: =IF(C28="","",(C28*E28))
A29: J | B29: Metal partitions - 12.5mm Board, 50mm Gyplyner, 12.5mm board | D29: m2 | F29: =IF(C29="","",(C29*E29))
F30: =IF(C30="","",(C30*E30))
A31: K | B31: Metal partitions with insulation - 12.5mm Board, 50mm Gyplyner, 50mm Isover, 12.5mm board | D31: m2 | F31: =IF(C31="","",(C31*E31))
F32: =IF(C32="","",(C32*E32))
A33: L | B33: Timber Partitions with Insulation - 12.5mm Board, 89 Timber Stud(by Others), 50mm Isover, 12.5mm board | C33: =((17*2.5)*6)+((13*2.5)*6) -> 450 | D33: m2 | E33: 11.52 | F33: =IF(C33="","",(C33*E33)) -> 5184
F34: =IF(C34="","",(C34*E34))
A35: M | B35: Timber Partitions (Dwarf Walls) - 12.5mm Board, 89 Timber Stud(by Others), 50mm Isover, 12.5mm board | C35: =12.76*6 -> 76.56 | D35: m2 | E35: 11.52 | F35: =IF(C35="","",(C35*E35)) -> 881.9712
F36: =IF(C36="","",(C36*E36))
A37: N | B37: Eo Ply patressing | D37: m2 | F37: =IF(C37="","",(C37*E37))
F38: =IF(C38="","",(C38*E38))
A39: O | B39: Eo moisture board | C39: =(((9*2.5)+0.66)*6)+((6.25*2.5)*6)+((9.25*2.5)*6) -> 371.46 | D39: m2 | E39: 7.25 | F39: =IF(C39="","",(C39*E39)) -> 2693.085
F40: =IF(C40="","",(C40*E40))
A41: P | B41: Eo tape & joint | C41: =C35+C33+C27+C25 -> 1831.56 | D41: m2 | E41: 6 | F41: =IF(C41="","",(C41*E41)) -> 10989.36
F42: =IF(C42="","",(C42*E42))
D44: To collection | E44: £ | F44: =SUM(F5:F43) -> 75347.111
A47: Q | B47: Eo Skim | C47: =C41 -> 1831.56 | D47: m2 | E47: 7 | F47: =IF(C47="","",(C47*E47)) -> 12820.92
F48: =IF(C48="","",(C48*E48))
B49: Insulation | F49: =IF(C49="","",(C49*E49))
F50: =IF(C50="","",(C50*E50))
A51: R | B51: 200mm APR 1200mm to floor zone | C51: =C7*2 -> 512 | D51: m2 | E51: 5 | F51: =IF(C51="","",(C51*E51)) -> 2560
F52: =IF(C52="","",(C52*E52))
A53: S | B53: Roof space - 500mm loft roll | C53: =29*4.49 -> 130.21 | D53: m2 | E53: 16.8 | F53: =IF(C53="","",(C53*E53)) -> 2187.528
F54: =IF(C54="","",(C54*E54))
B55: Boxings / Misc | F55: =IF(C55="","",(C55*E55))
F56: =IF(C56="","",(C56*E56))
B57: SVPS cw Access Panels | F57: =IF(C57="","",(C57*E57))
A58: T | B58: GF | C58: 6 | D58: no | E58: 135 | F58: =IF(C58="","",(C58*E58)) -> 810
A59: U | B59: FF | C59: 6 | D59: no | E59: 135 | F59: =IF(C59="","",(C59*E59)) -> 810
F60: =IF(C60="","",(C60*E60))
A61: V | B61: Bulkheads to stairs | C61: 12 | D61: no | E61: 135 | F61: =IF(C61="","",(C61*E61)) -> 1620
F62: =IF(C62="","",(C62*E62))
A63: W | B63: Bathroom Full Height Boxings | C63: 6 | D63: no | E63: 135 | F63: =IF(C63="","",(C63*E63)) -> 810
A64: X | B64: Bathroom Niches - 200mm x 200mm | D64: no | F64: =IF(C64="","",(C64*E64))
A65: Y | B65: Rooflights Reveals | C65: 18 | D65: no | E65: 250 | F65: =IF(C65="","",(C65*E65)) -> 4500
F66: =IF(C66="","",(C66*E66))
A67: Z | B67: Making Good | C67: 6 | D67: no | E67: 300 | F67: =IF(C67="","",(C67*E67)) -> 1800
F68: =IF(C68="","",(C68*E68))
B69: Render | F69: =IF(C69="","",(C69*E69))
F70: =IF(C70="","",(C70*E70))
A71: AA | B71: Monocouche Weberpral M - Chalk | C71: 123 | D71: m2 | E71: 55 | F71: =IF(C71="","",(C71*E71)) -> 6765
D74: To collection | E74: £ | F74: =SUM(F46:F73) -> 34683.448
B77: Block B
A79: AB | B79: 75mm sand and cement screed laid on 150mm PIR Kingspan Thermafloor TF70 insulation, Gas Radon DPM. | C79: 89 | D79: m2 | E79: 55 | F79: =IF(C79="","",(C79*E79)) -> 4895
F80: =IF(C80="","",(C80*E80))
B81: Ceilings | F81: =IF(C81="","",(C81*E81))
A82: AC | B82: 1no layer of 15mm wallboard | D82: m2 | F82: =IF(C82="","",(C82*E82))
F83: =IF(C83="","",(C83*E83))
A84: AD | B84: 1no layer of 15mm fireline wallboard | C84: =(41.64*4)+(10.13*2.11) -> 187.9343 | D84: m2 | E84: 12.5 | F84: =IF(C84="","",(C84*E84)) -> 2349.1788
F85: =IF(C85="","",(C85*E85))
A86: AE | B86: Skeilings - 120mm Kooltherm K107, 82.5mm Kooltherm K118 Insulated Board | C86: =5.03*10.13 -> 50.9539 | D86: m2 | E86: 70 | F86: =IF(C86="","",(C86*E86)) -> 3566.773
F87: =IF(C87="","",(C87*E87))
A88: AF | B88: EO moisture board | C88: =12.47*2 -> 24.94 | D88: m2 | E88: 7.25 | F88: =IF(C88="","",(C88*E88)) -> 180.815
F89: =IF(C89="","",(C89*E89))
A90: AG | B90: Eo tape & joint | C90: 238.8882 | D90: m2 | E90: 6 | F90: =IF(C90="","",(C90*E90)) -> 1433.3292
A92: AH | B92: EO Skim Finish | C92: =C84+C86 -> 238.8882 | D92: m2 | E92: 7 | F92: =IF(C92="","",(C92*E92)) -> 1672.2174
F93: =IF(C93="","",(C93*E93))
B94: Walls | F94: =IF(C94="","",(C94*E94))
F95: =IF(C95="","",(C95*E95))
A96: AI | B96: Dot & dab external walls | C96: =(21.74*2.5)*2 -> 108.7 | D96: m2 | E96: 11.6 | F96: =IF(C96="","",(C96*E96)) -> 1260.92
F97: =IF(C97="","",(C97*E97))
A98: AJ | B98: Dot & dab internal blockwork walls | D98: m2 | F98: =IF(C98="","",(C98*E98))
F99: =IF(C99="","",(C99*E99))
A100: AK | B100: Metal partitions - 12.5mm Board, 50mm Gyplyner, 12.5mm board | D100: m2 | F100: =IF(C100="","",(C100*E100))
F101: =IF(C101="","",(C101*E101))
A102: AL | B102: Timber partitions - 12.5mm Board, 89 Timber Stud(by Others), 12.5mm board | D102: m2 | F102: =IF(C102="","",(C102*E102))
F103: =IF(C103="","",(C103*E103))
A104: AM | B104: Timber Partitions with Insulation - 12.5mm Board, 89 Timber Stud(by Others), 50mm Isover, 12.5mm board | C104: =(40.11*2.5)*2 -> 200.55 | D104: m2 | E104: 11.52 | F104: =IF(C104="","",(C104*E104)) -> 2310.336
F105: =IF(C105="","",(C105*E105))
A106: AN | B106: Timber Partitions (Dwarf Walls) - 12.5mm Board, 89 Timber Stud(by Others), 50mm Isover, 12.5mm board | C106: 22.832 | D106: m2 | E106: 11.52 | F106: =IF(C106="","",(C106*E106)) -> 263.02464
F107: =IF(C107="","",(C107*E107))
A108: AO | B108: Eo Ply patressing | D108: m2 | F108: =IF(C108="","",(C108*E108))
F109: =IF(C109="","",(C109*E109))
A110: AP | B110: Eo moisture board | C110: =32.5+47.35+47.75 -> 127.6 | D110: m2 | E110: 7.25 | F110: =IF(C110="","",(C110*E110)) -> 925.1
F111: =IF(C111="","",(C111*E111))
A112: AQ | B112: Eo tape & joint | C112: =C106+C104+C96 -> 332.082 | D112: m2 | E112: 6 | F112: =IF(C112="","",(C112*E112)) -> 1992.492
...

Sheet 06 M&E
A2: =Summary!A2 -> The Former Police Station, Haslingden | D2: MECHANICAL & ELECTRICAL | F2: SECTION 6
B4: Description | C4: Quantity | D4: Unit | E4: Rate | F4: Total | G4: Comments
B6: Block A
A8: A | B8: Mechanical Provisional sum allowed for each unit. Mechanical drawings required along with a full client spec to be able to price works fully. Thermostatic heating system, Baxi Ecoblue 32 system boiler with cylinder. | C8: 6 | D8: plots | E8: 16800 | F8: =IF(C8="","",(C8*E8)) -> 100800 | G8: Including basic sanitaryware spec. Awaiting further confirmation.
B10: Block B
A12: B | B12: Mechanical Provisional sum allowed for each unit. Mechanical drawings required along with a full client spec to be able to price works fully. Thermostatic heating system, Baxi Ecoblue 32 system boiler with cylinder. | C12: 2 | D12: plots | E12: 16800 | F12: =IF(C12="","",(C12*E12)) -> 33600 | G12: Including basic sanitaryware spec. Awaiting further confirmation.
B14: Block A
A16: C | B16: Based on BG electrical Nexus accessories, need confirmation on exact spec. Allowed for white accessories only, pendant light fittings throughout. No allowance for any vehicle car charging points. | C16: 6 | D16: plots | E16: 4250 | F16: =IF(C16="","",(C16*E16)) -> 25500
B18: Block B
A20: D | B20: Based on BG electrical Nexus accessories, need confirmation on exact spec. Allowed for white accessories only, pendant light fittings throughout. No allowance for any vehicle car charging points. | C20: 2 | D20: plots | E20: 4250 | F20: =IF(C20="","",(C20*E20)) -> 8500
G26: =IF(D26="","",(D26*F26))
G27: =IF(D27="","",(D27*F27))
G30: =IF(D30="","",(D30*F30))
G31: =IF(D31="","",(D31*F31))
D38: To collection | E38: £ | F38: =SUM(F6:F36) -> 168400
D74: To collection | E74: £ | F74: =SUM(F40:F72) -> 0
F76: =IF(C76="","",(C76*E76))
C99: To Main Summary £ | F99: =SUM(F76:F97) -> 0

Sheet 07 Carpentry
A2: ='02 Plot Groundworks'!A2 -> The Former Police Station, Haslingden | D2: CARPENTRY | F2: SECTION 7
B4: Description | C4: Quantity | D4: Unit | E4: Rate | F4: Total | G4: Comments
B6: Block A
A8: A | B8: Externals
A10: B | B10: Easi joist floor system at 400mm centers including 22mm T&G chipboard decking incl trimming out, temp bracing & perimeter noggins | C10: =45*6 -> 270 | D10: m2 | E10: 19 | F10: =IF(C10="","",(C10*E10)) -> 5130
F11: =IF(C11="","",(C11*E11))
A12: C | B12: Cut & fix wall / pole plate (including halving joints where required). | C12: =29*6 -> 174 | D12: m | E12: 3 | F12: =IF(C12="","",(C12*E12)) -> 522
F13: =IF(C13="","",(C13*E13))
A14: D | B14: Attic trusses inc all fixings | C14: 72 | D14: no | E14: 45 | F14: =IF(C14="","",(C14*E14)) -> 3240
F15: =IF(C15="","",(C15*E15))
A16: E | B16: Fix 100 x 25mm longitudinal bracing to trusses (no detail, assummed) | C16: 6 | D16: plot | E16: 75 | F16: =IF(C16="","",(C16*E16)) -> 450
F17: =IF(C17="","",(C17*E17))
A18: F | B18: Install lateral restraint straps (on support noggins). | C18: =C12/2+1 -> 88 | D18: each | E18: 2.5 | F18: =IF(C18="","",(C18*E18)) -> 220
F19: =IF(C19="","",(C19*E19))
A20: G | B20: Cut & fix UPVC fascia board. | C20: =28.12*2 -> 56.24 | D20: m | E20: 4 | F20: =IF(C20="","",(C20*E20)) -> 224.96
F21: =IF(C21="","",(C21*E21))
A22: H | B22: Cut & fix bargeboard | C22: =13*2 -> 26 | D22: m | E22: 4 | F22: =IF(C22="","",(C22*E22)) -> 104
F23: =IF(C23="","",(C23*E23))
A24: I | B24: Cut & fix UPVC soffit. | C24: =C20+C22 -> 82.24 | D24: m | E24: 4 | F24: =IF(C24="","",(C24*E24)) -> 328.96
F25: =IF(C25="","",(C25*E25))
A26: J | B26: Fix Velux Window | C26: 18 | D26: no | E26: 50 | F26: =IF(C26="","",(C26*E26)) -> 900
F27: =IF(C27="","",(C27*E27))
B28: 1st Fix | F28: =IF(C28="","",(C28*E28))
F29: =IF(C29="","",(C29*E29))
A30: K | B30: Fix pre-hung PAS 24 entrance door set with pre-fitted muliti point lock (20mm total packing max) (sub-frame excluded). | C30: 6 | D30: plot | E30: 100 | F30: =IF(C30="","",(C30*E30)) -> 600
F31: =IF(C31="","",(C31*E31))
A32: L | B32: Cut protection panels from 9mm plywood for bath & shower tray (hand to plumber for installation). | C32: 6 | D32: set | E32: 50 | F32: =IF(C32="","",(C32*E32)) -> 300
F33: =IF(C33="","",(C33*E33))
A34: M | B34: Cut & fix window board (mdf, pre formed) (brackets supplied by Client) (window to be fitted with receiver groove by others). | C34: 36 | D34: m | E34: 5 | F34: =IF(C34="","",(C34*E34)) -> 180
F35: =IF(C35="","",(C35*E35))
A36: N | B36: Application of free-issue expanding foam to void below window cill. | C36: =C34 -> 36 | D36: m | E36: 1 | F36: =IF(C36="","",(C36*E36)) -> 36
F37: =IF(C37="","",(C37*E37))
A38: O | B38: Removal of sacraficial joists, hangers, flooring & access hatch to stairwell prior to stair installation. | C38: 12 | D38: floor | E38: 50 | F38: =IF(C38="","",(C38*E38)) -> 600
F39: =IF(C39="","",(C39*E39))
A40: P | B40: Install pre-assembled sw stair case (kite top & bottom) (full assembly & installation inclusive of string mounted newel posts, framing to support base of stair case & "T" bar support to rear of 1st riser). | C40: 12 | D40: each | E40: 450 | F40: =IF(C40="","",(C40*E40)) -> 5400
F41: =IF(C41="","",(C41*E41))
A42: Q | B42: Install temporary handrail to stair perimeter. | C42: 12 | D42: floor | E42: 75 | F42: =IF(C42="","",(C42*E42)) -> 900
C45: To Main Summary £ | F45: =SUM(F6:F44) -> 19135.92
A48: R | B48: Application of protection to staircase (materials provided by Client). | C48: 12 | D48: each | E48: 20 | F48: =IF(C48="","",(C48*E48)) -> 240
F49: =IF(C49="","",(C49*E49))
A50: S | B50: Cut and fit 38x68mm soleplate, header and mid supporting rail | C50: =38*6 -> 228 | D50: m | E50: 12 | F50: =IF(C50="","",(C50*E50)) -> 2736
F51: =IF(C51="","",(C51*E51))
A52: T | B52: Partitions for above set at 600mm cts | C52: =C50 -> 228 | D52: m | E52: 6 | F52: =IF(C52="","",(C52*E52)) -> 1368
F53: =IF(C53="","",(C53*E53))
A54: U | B54: Noggins and pattressing to partitions for other trades (average of 15no. Per plot). | C54: 6 | D54: plot | E54: 50 | F54: =IF(C54="","",(C54*E54)) -> 300
F55: =IF(C55="","",(C55*E55))
A56: V | B56: Cut out & form a 'letter box' aperture within the 2nd floor to enable sheet materials to be distributed from the 1st to 2nd floors. | C56: 6 | D56: each | E56: 25 | F56: =IF(C56="","",(C56*E56)) -> 150
F57: =IF(C57="","",(C57*E57))
A58: W | B58: Install support noggins & replace flooring to 'letter box' aperture following completion of loading out phase. | C58: 6 | D58: each | E58: 50 | F58: =IF(C58="","",(C58*E58)) -> 300
F59: =IF(C59="","",(C59*E59))
B60: 2nd Fix | F60: =IF(C60="","",(C60*E60))
F61: =IF(C61="","",(C61*E61))
A62: X | B62: Cut & fix skirting board (nailed & bonded, excluding full height window / patio door positions). | C62: =116*6 -> 696 | D62: m | E62: 5.5 | F62: =IF(C62="","",(C62*E62)) -> 3828
F63: =IF(C63="","",(C63*E63))
A64: Y | B64: Fix internal door lining to partition | C64: 66 | D64: each | E64: 15 | F64: =IF(C64="","",(C64*E64)) -> 990
F65: =IF(C65="","",(C65*E65))
A66: Z | B66: Fix MDF door stop set to door lining. | C66: 66 | D66: set | E66: 1 | F66: =IF(C66="","",(C66*E66)) -> 66
F67: =IF(C67="","",(C67*E67))
A68: AA | B68: Cut and fix architrave (both sides) | C68: 66 | D68: set | E68: 5 | F68: =IF(C68="","",(C68*E68)) -> 330
F69: =IF(C69="","",(C69*E69))
A70: AB | B70: Hang internal doors. | C70: 66 | D70: each | E70: 35 | F70: =IF(C70="","",(C70*E70)) -> 2310
F71: =IF(C71="","",(C71*E71))
A72: AC | B72: Cut down doors for carpet clearance at 2nd fix stage (linings supplied with 15-20mm tolerance as standard). | C72: 48 | D72: each | E72: 8 | F72: =IF(C72="","",(C72*E72)) -> 384
F73: =IF(C73="","",(C73*E73))
A74: AD | B74: Install standard butt hinge (3no. Per door leaf). | C74: 66 | D74: each | E74: 5 | F74: =IF(C74="","",(C74*E74)) -> 330
F75: =IF(C75="","",(C75*E75))
A76: AF | B76: Cut out for & fit privacy mortise lock (if required). | C76: 18 | D76: each | E76: 2 | F76: =IF(C76="","",(C76*E76)) -> 36
F77: =IF(C77="","",(C77*E77))
A78: AG | B78: Make & fit slatted shelving & supports to airing cupboard 2no. per unit. | C78: 12 | D78: each | E78: 25 | F78: =IF(C78="","",(C78*E78)) -> 300
C81: To Main Summary £ | F81: =SUM(F47:F79) -> 13668
A85: AH | B85: Cut & fix pre-fabricated balustrade panels to softwood staircases (inclusive of handrail). | C85: =12*6 -> 72 | D85: m | E85: 15 | F85: =IF(C85="","",(C85*E85)) -> 1080
F86: =IF(C86="","",(C86*E86))
A87: AI | B87: Cut & fix wall mounted "pigs ear" handrail to outer wall of staircases. | D87: m | F87: =IF(C87="","",(C87*E87)) | G87: N/A
F88: =IF(C88="","",(C88*E88))
B89: Final Fix | F89: =IF(C89="","",(C89*E89))
F90: =IF(C90="","",(C90*E90))
A91: AJ | B91: Fit lever handles to FED & secondary door multi point lock. | C91: 6 | D91: each | E91: 10 | F91: =IF(C91="","",(C91*E91)) -> 60
F92: =IF(C92="","",(C92*E92))
A93: AK | B93: Fit security door chain to FED. | C93: 6 | D93: each | E93: 10 | F93: =IF(C93="","",(C93*E93)) -> 60
F94: =IF(C94="","",(C94*E94))
A95: AL | B95: Fit door numerals to FED. | C95: 6 | D95: each | E95: 10 | F95: =IF(C95="","",(C95*E95)) -> 60
F96: =IF(C96="","",(C96*E96))
A97: AM | B97: Fit lever handles to internal doors (1no. pair allocated to single doors only). | C97: =C74 -> 66 | D97: each | E97: 10 | F97: =IF(C97="","",(C97*E97)) -> 660
F98: =IF(C98="","",(C98*E98))
A99: AN | B99: Fit privacy handles to bathrooms, en-suites & WC's. | C99: 18 | D99: each | E99: 10 | F99: =IF(C99="","",(C99*E99)) -> 180
F100: =IF(C100="","",(C100*E100))
A101: AO | B101: Fit skirting & floor mounted door buffer stops. | C101: 66 | D101: each | E101: 4.5 | F101: =IF(C101="","",(C101*E101)) -> 297
F102: =IF(C102="","",(C102*E102))
A103: AP | B103: Snagging | C103: 6 | D103: plot | E103: 140 | F103: =IF(C103="","",(C103*E103)) -> 840
F104: =IF(C104="","",(C104*E104))
B105: Low level roofs and porches | F105: =IF(C105="","",(C105*E105))
F106: =IF(C106="","",(C106*E106))
A107: AQ | B107: Construct Lean to Timber Door Canopy, ready to be tiled by others,100xm38mm sw rafters, 220x75mm sw bearer @ 5.4m long | C107: 3 | D107: no | E107: 300 | F107: =IF(C107="","",(C107*E107)) -> 900
F108: =IF(C108="","",(C108*E108))
F109: =IF(C109="","",(C109*E109))
F110: =IF(C110="","",(C110*E110))
F111: =IF(C111="","",(C111*E111))
F112: =IF(C112="","",(C112*E112))
F113: =IF(C113="","",(C113*E113))
F114: =IF(C114="","",(C114*E114))
...

Sheet 08 Roof Coverings
A2: =Summary!A2 -> The Former Police Station, Haslingden | D2: ROOF COVERINGS | F2: SECTION 8
B4: Description | C4: Quantity | D4: Unit | E4: Rate | F4: Total | G4: Comments
B6: Block A
A8: A | B8: Main roofs and canopies - Sobrano brazilian grey / green natural slate. Battened out to the appropriate gauge and fixed to a breather membrane. To include all ridge and verge operations as well as leadwork where required. Porches to be smaller format tiles. | C8: =((6.334*2)*28.175)+16.52 -> 373.4409 | D8: m2 | E8: 135 | F8: =IF(C8="","",(C8*E8)) -> 50414.521
B10: Block B
A12: B | B12: Main roofs and canopies - Sobrano brazilian grey / green natural slate. Battened out to the appropriate gauge and fixed to a breather membrane. To include all ridge and verge operations as well as leadwork where required. Porches to be smaller format tiles. | C12: =((5.538*2)*10.85)+5.51 -> 125.6846 | D12: m2 | E12: 135 | F12: =IF(C12="","",(C12*E12)) -> 16967.421
G26: =IF(D26="","",(D26*F26))
G27: =IF(D27="","",(D27*F27))
G30: =IF(D30="","",(D30*F30))
G31: =IF(D31="","",(D31*F31))
D38: To collection | E38: £ | F38: =SUM(F6:F36) -> 67381.943
D74: To collection | E74: £ | F74: =SUM(F40:F72) -> 0
F76: =IF(C76="","",(C76*E76))
C99: To Main Summary £ | F99: =SUM(F76:F97) -> 0

Sheet 09 Decorating & Other Finishing
A2: ='02 Plot Groundworks'!A2 -> The Former Police Station, Haslingden | D2: DECORATION | F2: SECTION 9
D3: & OTHER FINISHING TRADES
B4: Description | C4: Quantity | D4: Unit | E4: Rate | F4: Total | G4: Comments
B6: Decoration
B8: Block A
A10: A | B10: Decoration, emulsion to walls and ceilings with glosswork for all internal woodwork. | C10: 7686 | D10: £/SQFT | E10: 4 | F10: =IF(C10="","",(C10*E10)) -> 30744 | G10: Assumed no colours or wallpapering, no coving or any other ornate details. Assumed timeless white to both walls and ceilings.
B12: Block B
A14: B | B14: Decoration, emulsion to walls and ceilings with glosswork for all internal woodwork. | C14: 2456 | D14: £/SQFT | E14: 4 | F14: =IF(C14="","",(C14*E14)) -> 9824 | G14: Assumed no colours or wallpapering, no coving or any other ornate details. Assumed dulux timeless white to both walls and ceilings.
B16: Mastic
B18: Block A
A20: C | B20: Mastic works to internal floor junctions for tiled / laminate flooring, internal window frames, junction between wall tiling and wall, kitchen worktop corner junction between wall tiling. Externals - around window frames, meter box, movement joints, porches (where required) | C20: 7686 | D20: £/SQFT | E20: 0.5 | F20: =IF(C20="","",(C20*E20)) -> 3843
B22: Block B
A24: D | B24: Mastic works to internal floor junctions for tiled / laminate flooring, internal window frames, junction between wall tiling and wall, kitchen worktop corner junction between wall tiling. Externals - around window frames, meter box, movement joints, porches (where required) | C24: 2456 | D24: £/SQFT | E24: 0.5 | F24: =IF(C24="","",(C24*E24)) -> 1228
F25: =IF(C25="","",(C25*E25))
B26: Kitchens
B28: Block A | F28: =IF(C28="","",(C28*E28))
F29: =IF(C29="","",(C29*E29))
A30: E | B30: Kitchen supply and installation including appliacnes and standard 45mm MDF worktop. Spec required in order to sure up pricing for this element of works. | C30: 6 | D30: plot | E30: 12500 | F30: =IF(C30="","",(C30*E30)) -> 75000 | G30: No allowance for granite unless otherwise specified. Appliances allowed from the Bosch group. Oven, hob, extractor, FF, Dishwasher & washing machine.
F31: =IF(C31="","",(C31*E31))
B32: Block B | F32: =IF(C32="","",(C32*E32))
F33: =IF(C33="","",(C33*E33))
A34: F | B34: Kitchen supply and installation including appliacnes and standard 45mm MDF worktop. Spec required in order to sure up pricing for this element of works. | C34: 2 | D34: plot | E34: 12500 | F34: =IF(C34="","",(C34*E34)) -> 25000 | G34: No allowance for granite unless otherwise specified. Appliances allowed from the Bosch group. Oven, hob, extractor, FF, Dishwasher & washing machine
F35: =IF(C35="","",(C35*E35))
B36: Wall tiling | F36: =IF(C36="","",(C36*E36)) | G36: Tiling spec to be from the basic range from Porcelonsa.
F37: =IF(C37="","",(C37*E37))
B38: Block A | F38: =IF(C38="","",(C38*E38))
F39: =IF(C39="","",(C39*E39))
A40: G | B40: WC - half height around sanitaryware walls, 2 sides | C40: =(3.13*1.25)*6 -> 23.475 | D40: m2 | E40: 75 | F40: =IF(C40="","",(C40*E40)) -> 1760.625
A41: H | B41: Bathroom - half height and shelf tiled, full height around bath | C41: =((2*1.2)+(2*0.33)+(2.58*2))*6 -> 49.32 | D41: m2 | E41: 75 | F41: =IF(C41="","",(C41*E41)) -> 3699
A42: I | B42: Ensuite - half height tiling to wash hand basin wall | C42: =(2.38*1.2)*6 -> 17.136 | D42: m2 | E42: 75 | F42: =IF(C42="","",(C42*E42)) -> 1285.2
A43: J | B43: Ensuite - tiled dwarf wall (not skeiling) | C43: =(2.24*1.5)*6 -> 20.16 | D43: m2 | E43: 75 | F43: =IF(C43="","",(C43*E43)) -> 1512
A44: K | B44: Ensuite - full height tiling around shower | C44: =(1.63*2.5)*6 -> 24.45 | D44: m2 | E44: 75 | F44: =IF(C44="","",(C44*E44)) -> 1833.75
F45: =IF(C45="","",(C45*E45))
B46: Block B | F46: =IF(C46="","",(C46*E46))
F47: =IF(C47="","",(C47*E47))
A48: L | B48: WC - half height around sanitaryware walls, 2 sides | C48: =(3.25*1.25)*2 -> 8.125 | D48: m2 | E48: 75 | F48: =IF(C48="","",(C48*E48)) -> 609.375
A49: M | B49: Bathroom - half height and shelf tiled, full height around bath | C49: =((2*1.2)+(2*0.33)+(2.4*2))*2 -> 15.72 | D49: m2 | E49: 75 | F49: =IF(C49="","",(C49*E49)) -> 1179
A50: N | B50: Ensuite - half height tiling to wash hand basin wall | C50: =(1.93*1.2)*2 -> 4.632 | D50: m2 | E50: 75 | F50: =IF(C50="","",(C50*E50)) -> 347.4
A51: O | B51: Ensuite - tiled dwarf wall (not skeiling) | C51: =(2.84*1.2)*2 -> 6.816 | D51: m2 | E51: 75 | F51: =IF(C51="","",(C51*E51)) -> 511.2
A52: P | B52: Ensuite - full height tiling around shower | C52: =(1.63*2.5)*2 -> 8.15 | D52: m2 | E52: 75 | F52: =IF(C52="","",(C52*E52)) -> 611.25
F53: =IF(C53="","",(C53*E53))
F54: =IF(C54="","",(C54*E54))
F55: =IF(C55="","",(C55*E55))
D57: To collection | E57: £ | F57: =SUM(F7:F56) -> 158987.8
B60: Floor Tiling | G60: Tiling spec to be from the basic range from Porcelonsa.
B62: Block A
A64: Q | B64: Floor tiling to kitchen / dining, bathroom, ensuite | C64: =22*6 -> 132 | D64: m2 | E64: 75 | F64: =IF(C64="","",(C64*E64)) -> 9900
F65: =IF(C65="","",(C65*E65))
B66: Block B | F66: =IF(C66="","",(C66*E66))
F67: =IF(C67="","",(C67*E67))
A68: R | B68: Floor tiling to kitchen / dining, bathroom, ensuite | C68: =24*2 -> 48 | D68: m2 | E68: 75 | F68: =IF(C68="","",(C68*E68)) -> 3600
F69: =IF(C69="","",(C69*E69))
B70: Carpets | F70: =IF(C70="","",(C70*E70))
F71: =IF(C71="","",(C71*E71))
B72: Block A | F72: =IF(C72="","",(C72*E72))
F73: =IF(C73="","",(C73*E73))
A74: S | B74: Carpets to lounge, store, hall, stairs, landing, store, bed 1, 2 & 3, store, landing | C74: =471+72+18 -> 561 | D74: m2 | E74: 30 | F74: =IF(C74="","",(C74*E74)) -> 16830
F75: =IF(C75="","",(C75*E75))
B76: Block B | F76: =IF(C76="","",(C76*E76))
F77: =IF(C77="","",(C77*E77))
A78: T | B78: Carpets to lounge, store, hall, stairs, landing, store, bed 1, 2 & 3, store, landing | C78: =(76+12)*2 -> 176 | D78: m2 | E78: 30 | F78: =IF(C78="","",(C78*E78)) -> 5280
F79: =IF(C79="","",(C79*E79))
B80: Cleaning | F80: =IF(C80="","",(C80*E80))
F81: =IF(C81="","",(C81*E81))
B82: Block A | F82: =IF(C82="","",(C82*E82))
F83: =IF(C83="","",(C83*E83))
A84: U | B84: Builders, re-clean and sparkle allowed to each unit. | C84: 6 | D84: plot | E84: 650 | F84: =IF(C84="","",(C84*E84)) -> 3900
F85: =IF(C85="","",(C85*E85))
B86: Block B | F86: =IF(C86="","",(C86*E86))
F87: =IF(C87="","",(C87*E87))
A88: V | B88: Builders, re-clean and sparkle allowed to each unit. | C88: 2 | D88: plot | E88: 650 | F88: =IF(C88="","",(C88*E88)) -> 1300
F89: =IF(C89="","",(C89*E89))
F90: =IF(C90="","",(C90*E90))
F91: =IF(C91="","",(C91*E91))
F92: =IF(C92="","",(C92*E92))
F93: =IF(C93="","",(C93*E93))
F94: =IF(C94="","",(C94*E94))
D97: To collection | E97: £ | F97: =SUM(F59:F96) -> 40810
F131: =IF(C131="","",(C131*E131))
D134: To collection | E134: £ | F134: =SUM(F99:F133) -> 0
F166: =IF(C166="","",(C166*E166))
D169: To collection | E169: £ | F169: =SUM(F137:F168) -> 0
D211: To collection | E211: £ | F211: =SUM(F171:F209) -> 0
D243: To collection | E243: £ | F243: =SUM(F213:F241) -> 0
C274: To Main Summary £ | F274: =SUM(F245:F272) -> 0

Sheet 10 Materials
A2: ='02 Plot Groundworks'!A2 -> The Former Police Station, Haslingden | D2: MATERIALS | F2: SECTION 10
B4: Description | C4: Quantity | D4: Unit | E4: Rate | F4: Total | G4: Comments
B6: BLOCK A
A8: A | B8: Radon DPC | C8: 77 | D8: m | E8: 9 | F8: =IF(C8="","",(C8*E8)) -> 693
F9: =IF(C9="","",(C9*E9))
A10: B | B10: 100m bradstone or similar bed coursed artificial stone above DPC | C10: =326*1.1 -> 358.6 | D10: m2 | E10: 41 | F10: =IF(C10="","",(C10*E10)) -> 14702.6
F11: =IF(C11="","",(C11*E11))
A12: C | B12: 75mm Kingspan TW Thermawall cavity board | C12: 448 | D12: m2 | E12: 38 | F12: =IF(C12="","",(C12*E12)) -> 17024
A14: D | B14: 100mm concrete blockwork to inner leaf above DPC | C14: 448 | D14: m2 | E14: 19 | F14: =IF(C14="","",(C14*E14)) -> 8512
F15: =IF(C15="","",(C15*E15))
A16: E | B16: 100mm blockwork to internal walls | C16: =((15*2.5)*6)*1.1 -> 247.5 | D16: m2 | E16: 19 | F16: =IF(C16="","",(C16*E16)) -> 4702.5
A18: F | B18: 100mm concrete blocks to party wall including gable, lightweight aggregate blocks | C18: 838 | D18: m2 | E18: 20 | F18: =IF(C18="","",(C18*E18)) -> 16760
A20: G | B20: 100mm Isover RD Party Wall Insulation | C20: 419 | D20: m2 | E20: 9.5 | F20: =IF(C20="","",(C20*E20)) -> 3980.5
A22: H | B22: 100mm concrete blockwork to outer leaf to rendered sections including any bed joint reinforcement required | C22: 135 | D22: m2 | E22: 20 | F22: =IF(C22="","",(C22*E22)) -> 2700
A24: I | B24: Steel lintels | C24: 71 | D24: m | E24: 47.5 | F24: =IF(C24="","",(C24*E24)) -> 3372.5
A26: J | B26: Ashlar stone heads and cills | C26: 105 | D26: m | E26: 118 | F26: =IF(C26="","",(C26*E26)) -> 12390
A28: K | B28: DPC / Cavity Trays | C28: 71 | D28: m | E28: 0.65 | F28: =IF(C28="","",(C28*E28)) -> 46.15
A30: L | B30: Mortar | C30: =C22+C18+C16+C14+C10 -> 2027.1 | D30: m2 | E30: 6.1 | F30: =IF(C30="","",(C30*E30)) -> 12365.31 | H30: 90 | I30: m3
H31: Brick | I31: 0.108 | J31: =SUM(C10) -> 358.6 | K31: =J31*I31 -> 38.7288 | L31: =K31*H30 -> 3485.592
A32: M | B32: Cavity Formers | C32: 6 | D32: plots | E32: 400 | F32: =IF(C32="","",(C32*E32)) -> 2400 | H32: Block | I32: 0.059 | J32: =SUM(C22+C18+C16+C14) -> 1668.5 | K32: =J32*I32 -> 98.4415 | L32: =K32*H30 -> 8859.735
F33: =IF(C33="","",(C33*E33))
A34: N | B34: Misc brickwork sundries | C34: 6 | D34: plots | E34: 150 | F34: =IF(C34="","",(C34*E34)) -> 900 | L34: =SUM(L31:L32) -> 12345.327
A36: O | B36: Easi joists | C36: 6 | D36: plots | E36: 1700 | F36: =IF(C36="","",(C36*E36)) -> 10200
F37: =IF(C37="","",(C37*E37))
A38: P | B38: Attic Trusses | C38: 6 | D38: plots | E38: 6500 | F38: =IF(C38="","",(C38*E38)) -> 39000
F39: =IF(C39="","",(C39*E39))
A40: Q | B40: Fascia, Soffit & bargeboard | C40: 6 | D40: plots | E40: 550 | F40: =IF(C40="","",(C40*E40)) -> 3300
F41: =IF(C41="","",(C41*E41))
A42: R | B42: Velux windows - large | C42: 12 | D42: no | E42: 850 | F42: =IF(C42="","",(C42*E42)) -> 10200
F43: =IF(C43="","",(C43*E43))
A44: S | B44: Velux windows - small | C44: 6 | D44: no | E44: 550 | F44: =IF(C44="","",(C44*E44)) -> 3300
F45: =IF(C45="","",(C45*E45))
A46: T | B46: Staircases | C46: 6 | D46: plots | E46: 1375 | F46: =IF(C46="","",(C46*E46)) -> 8250 | G46: Including pre assembled ballustrade and handrail
F47: =IF(C47="","",(C47*E47))
A48: U | B48: Lean too Porches | C48: 6 | D48: plots | E48: 575 | F48: =IF(C48="","",(C48*E48)) -> 3450
F49: =IF(C49="","",(C49*E49))
A50: V | B50: 1st fix timbers | C50: 6 | D50: plots | E50: 350 | F50: =IF(C50="","",(C50*E50)) -> 2100
F51: =IF(C51="","",(C51*E51))
A52: W | B52: Internal doors - FD20 | C52: =6*6 -> 36 | D52: items | E52: 105 | F52: =IF(C52="","",(C52*E52)) -> 3780 | G52: Vertical 5 paneled primed, to be painted white on site.
F53: =IF(C53="","",(C53*E53))
A54: X | B54: Internal doors - std | C54: =5*6 -> 30 | D54: items | E54: 55 | F54: =IF(C54="","",(C54*E54)) -> 1650 | G54: Vertical 5 paneled primed, to be painted white on site.
F55: =IF(C55="","",(C55*E55))
A56: Y | B56: 2nd fix timbers | C56: 6 | D56: plots | E56: 725 | F56: =IF(C56="","",(C56*E56)) -> 4350 | G56: Standard penceil round skirting and architrave to come primed and glossed on site.
F57: =IF(C57="","",(C57*E57))
A58: Z | B58: Misc Joinery Sundries | C58: 6 | D58: plots | E58: 150 | F58: =IF(C58="","",(C58*E58)) -> 900
F59: =IF(C59="","",(C59*E59))
A60: AA | B60: Front door | C60: 6 | D60: items | E60: 475 | F60: =IF(C60="","",(C60*E60)) -> 2850 | G60: Standard black composite front door with UPVC frame. Glazing still to be determined, none allowed.
A61: AB | B61: Meter Boxes | C61: 6 | D61: items | E61: 90 | F61: =IF(C61="","",(C61*E61)) -> 540
F62: =IF(C62="","",(C62*E62))
A63: AC | B63: Ironmongery | C63: 6 | D63: plots | E63: 250 | F63: =IF(C63="","",(C63*E63)) -> 1500
D66: To collection | E66: £ | F66: =SUM(F5:F63) -> 195918.56
B69: BLOCK B
A71: AD | B71: Radon DPC | C71: 40 | D71: m | E71: 9 | F71: =IF(C71="","",(C71*E71)) -> 360
F72: =IF(C72="","",(C72*E72))
A73: AE | B73: 100m bradstone or similar bed coursed artificial stone above DPC | C73: =192*1.1 -> 211.2 | D73: m2 | E73: 41 | F73: =IF(C73="","",(C73*E73)) -> 8659.2
F74: =IF(C74="","",(C74*E74))
A75: AF | B75: 75mm Kingspan TW Thermawall cavity board | C75: 256.2 | D75: m2 | E75: 38 | F75: =IF(C75="","",(C75*E75)) -> 9735.6
A77: AG | B77: 100mm concrete blockwork to inner leaf above DPC | C77: 256.2 | D77: m2 | E77: 19 | F77: =IF(C77="","",(C77*E77)) -> 4867.8
F78: =IF(C78="","",(C78*E78))
A79: AH | B79: 100mm blockwork to internal walls | D79: m2 | F79: =IF(C79="","",(C79*E79)) | G79: N/A
A81: AI | B81: 100mm concrete blocks to party wall including gable, lightweight aggregate blocks | C81: 138 | D81: m2 | E81: 20 | F81: =IF(C81="","",(C81*E81)) -> 2760
A83: AJ | B83: 100mm Isover RD Party Wall Insulation | C83: 69 | D83: m2 | E83: 9.5 | F83: =IF(C83="","",(C83*E83)) -> 655.5
A85: AK | B85: 100mm concrete blockwork to outer leaf to rendered sections including any bed joint reinforcement required | C85: 45 | D85: m2 | E85: 20 | F85: =IF(C85="","",(C85*E85)) -> 900
A87: AL | B87: Steel lintels | C87: 29 | D87: m | E87: 47.5 | F87: =IF(C87="","",(C87*E87)) -> 1377.5
A89: AM | B89: Ashlar stone heads and cills | C89: 43 | D89: m | E89: 118 | F89: =IF(C89="","",(C89*E89)) -> 5074
A91: AN | B91: DPC / Cavity Trays | C91: 29 | D91: m | E91: 0.65 | F91: =IF(C91="","",(C91*E91)) -> 18.85
A93: AO | B93: Mortar | C93: =SUM(C85+C81+C75+C73) -> 650.4 | D93: item | E93: 6.1 | F93: =IF(C93="","",(C93*E93)) -> 3967.44
A95: AP | B95: Cavity Formers | C95: 2 | D95: plots | E95: 400 | F95: =IF(C95="","",(C95*E95)) -> 800
F96: =IF(C96="","",(C96*E96))
A97: AQ | B97: Misc brickwork sundries | C97: 2 | D97: plots | E97: 150 | F97: =IF(C97="","",(C97*E97)) -> 300
F98: =IF(C98="","",(C98*E98))
A99: AR | B99: Easi joists | C99: 2 | D99: plots | E99: 1700 | F99: =IF(C99="","",(C99*E99)) -> 3400
A101: AS | B101: Attic Trusses | C101: 2 | D101: plots | E101: 6500 | F101: =IF(C101="","",(C101*E101)) -> 13000
F102: =IF(C102="","",(C102*E102))
A103: AT | B103: Fascia, Soffit & bargeboard | C103: 2 | D103: plots | E103: 550 | F103: =IF(C103="","",(C103*E103)) -> 1100
F104: =IF(C104="","",(C104*E104))
A105: AU | B105: Velux windows - large | C105: 4 | D105: no | E105: 850 | F105: =IF(C105="","",(C105*E105)) -> 3400
F106: =IF(C106="","",(C106*E106))
A107: AV | B107: Velux windows - small | C107: 2 | D107: no | E107: 550 | F107: =IF(C107="","",(C107*E107)) -> 1100
F108: =IF(C108="","",(C108*E108))
A109: AW | B109: Staircases | C109: 2 | D109: plots | E109: 1375 | F109: =IF(C109="","",(C109*E109)) -> 2750 | G109: Including pre assembled ballustrade and handrail
F110: =IF(C110="","",(C110*E110))
A111: AX | B111: Lean too Porches | C111: 2 | D111: plots | E111: 575 | F111: =IF(C111="","",(C111*E111)) -> 1150
F112: =IF(C112="","",(C112*E112))
A113: AY | B113: 1st fix timbers | C113: 2 | D113: plots | E113: 350 | F113: =IF(C113="","",(C113*E113)) -> 700
F114: =IF(C114="","",(C114*E114))
A115: AZ | B115: Internal doors - FD20 | C115: =6*2 -> 12 | D115: items | E115: 105 | F115: =IF(C115="","",(C115*E115)) -> 1260 | G115: Vertical 5 paneled primed, to be painted white on site.
F116: =IF(C116="","",(C116*E116))
A117: BA | B117: Internal doors - std | C117: =5*2 -> 10 | D117: items | E117: 55 | F117: =IF(C117="","",(C117*E117)) -> 550 | G117: Vertical 5 paneled primed, to be painted white on site.
F118: =IF(C118="","",(C118*E118))
A119: BB | B119: 2nd fix timbers | C119: 2 | D119: plots | E119: 725 | F119: =IF(C119="","",(C119*E119)) -> 1450 | G119: Standard penceil round skirting and architrave to come primed and glossed on site.
F120: =IF(C120="","",(C120*E120))
A121: BC | B121: Misc Joinery Sundries | C121: 2 | D121: plots | E121: 150 | F121: =IF(C121="","",(C121*E121)) -> 300
F122: =IF(C122="","",(C122*E122))
A123: BD | B123: Front door | C123: 2 | D123: items | E123: =E60 -> 475 | F123: =IF(C123="","",(C123*E123)) -> 950 | G123: Standard black composite front door with UPVC frame
A125: BE | B125: Meter Boxes | C125: 2 | D125: items | E125: 90 | F125: =IF(C125="","",(C125*E125)) -> 180
F126: =IF(C126="","",(C126*E126))
A127: BF | B127: Ironmongery | C127: 2 | D127: plots | E127: 250 | F127: =IF(C127="","",(C127*E127)) -> 500
D130: To collection | E130: £ | F130: =SUM(F68:F127) -> 71265.89

Sheet 11 Landscaping
A2: ='02 Plot Groundworks'!A2 -> The Former Police Station, Haslingden | D2: LANDSCAPING | F2: SECTION 11
B4: Description | C4: Quantity | D4: Unit | E4: Rate | F4: Total | G4: Comments
B6: Landscaping | G6: No containised stock allowed. No ongoing maintence of turf or plants allowed, this can be allowed as an extra over. Rates include layer of organic mulch to trees, shrubs, plants and specimens.
A8: A | B8: Heavy standard tress av height 350cm - 425cm | C8: 2 | D8: no | E8: 750 | F8: =IF(C8="","",(C8*E8)) -> 1500
F9: =IF(C9="","",(C9*E9))
A10: B | B10: Shrubs - variety mix av height 30 - 60cm | C10: 128 | D10: no | E10: 13 | F10: =IF(C10="","",(C10*E10)) -> 1664
F11: =IF(C11="","",(C11*E11))
A12: C | B12: Specimens - av height 60 - 100cm | C12: 8 | D12: no | E12: 26 | F12: =IF(C12="","",(C12*E12)) -> 208
A14: D | B14: Hedges - double staggered row, av height 60 - 80cm | C14: 168 | D14: no | E14: 14.5 | F14: =IF(C14="","",(C14*E14)) -> 2436
F15: =IF(C15="","",(C15*E15))
A16: E | B16: Turfing allowed to landscaped areas | C16: 55 | D16: m2 | E16: 8 | F16: =IF(C16="","",(C16*E16)) -> 440
A18: F | B18: Turfing to front and rear gardens | C18: 262 | D18: m2 | E18: 8 | F18: =IF(C18="","",(C18*E18)) -> 2096
F20: =IF(C20="","",(C20*E20))
F22: =IF(C22="","",(C22*E22))
F24: =IF(C24="","",(C24*E24))
F26: =IF(C26="","",(C26*E26))
F28: =IF(C28="","",(C28*E28))
F30: =IF(C30="","",(C30*E30))
F32: =IF(C32="","",(C32*E32))
F33: =IF(C33="","",(C33*E33))
F34: =IF(C34="","",(C34*E34))
F35: =IF(C35="","",(C35*E35))
F36: =IF(C36="","",(C36*E36))
F37: =IF(C37="","",(C37*E37))
... F61: =IF(C61="","",(C61*E61))
D64: To collection | E64: £ | F64: =SUM(F5:F61) -> 8344
F69: =IF(C69="","",(C69*E69))
F70: =IF(C70="","",(C70*E70))
F71: =IF(C71="","",(C71*E71))
F72: =IF(C72="","",(C72*E72))
F73: =IF(C73="","",(C73*E73))
F81: =IF(C81="","",(C81*E81))
F83: =IF(C83="","",(C83*E83))
F85: =IF(C85="","",(C85*E85))
F87: =IF(C87="","",(C87*E87))
F89: =IF(C89="","",(C89*E89))
F91: =IF(C91="","",(C91*E91))
F93: =IF(C93="","",(C93*E93))
... F122: =IF(C122="","",(C122*E122))
D125: To collection | E125: £ | F125: =SUM(F66:F115) -> 0

Sheet 12 Walls & Fences
A2: ='02 Plot Groundworks'!A2 -> The Former Police Station, Haslingden | D2: WALLS & FENCES | F2: SECTION 12
B4: Description | C4: Quantity | D4: Unit | E4: Rate | F4: Total | G4: Comments
B6: Boundary walls
A8: A | B8: 1.2m high natural stone wall with 0.6m high timber fence attached | C8: 33 | D8: m | E8: 314 | F8: =IF(C8="","",(C8*E8)) -> 10362
F9: =IF(C9="","",(C9*E9))
A10: B | B10: 1.2m high natural stone wall (215mm wide) | C10: 58 | D10: m | E10: 264 | F10: =IF(C10="","",(C10*E10)) -> 15312 | H10: £ | I10: 60 | J10: m2 | K10: lay | L10: =I10*2 -> 120
F11: =IF(C11="","",(C11*E11)) | H11: £ | I11: 41 | J11: m2 | K11: Bricks | L11: =I11*2 -> 82
B12: Fencing | F12: =IF(C12="","",(C12*E12)) | H12: £ | I12: 6 | J12: m2 | K12: mortar | L12: =I12*2 -> 12
F13: =IF(C13="","",(C13*E13)) | H13: £ | I13: 3 | J13: m2 | K13: sundries | L13: =I13*2 -> 6
A14: C | B14: 1.8m high timber closeboard fence | C14: 168 | D14: m | E14: 65 | F14: =IF(C14="","",(C14*E14)) -> 10920
F15: =IF(C15="","",(C15*E15)) | L15: =SUM(L10:L14) -> 220
B16: Gates | F16: =IF(C16="","",(C16*E16)) | L16: 1.2
F17: =IF(C17="","",(C17*E17)) | L17: =L15*L16 -> 264
A18: D | B18: 1.2m high timber pedestrian gate | C18: 8 | D18: no | E18: 200 | F18: =IF(C18="","",(C18*E18)) -> 1600 | K18: timber fence | L18: 50
F19: =IF(C19="","",(C19*E19)) | L19: =L17+L18 -> 314
A20: E | B20: 1.8m high timber closeboard gate | C20: 8 | D20: no | E20: 250 | F20: =IF(C20="","",(C20*E20)) -> 2000
A22: F | B22: 2.65m wide timber vehicle gates | C22: 2 | D22: no | E22: 850 | F22: =IF(C22="","",(C22*E22)) -> 1700 | G22: Assumed timber
F24: =IF(C24="","",(C24*E24))
F26: =IF(C26="","",(C26*E26))
F28: =IF(C28="","",(C28*E28))
F30: =IF(C30="","",(C30*E30))
F32: =IF(C32="","",(C32*E32))
F33: =IF(C33="","",(C33*E33))
F34: =IF(C34="","",(C34*E34))
F35: =IF(C35="","",(C35*E35))
F36: =IF(C36="","",(C36*E36))
F37: =IF(C37="","",(C37*E37))
F38: =IF(C38="","",(C38*E38))
F39: =IF(C39="","",(C39*E39))
... F61: =IF(C61="","",(C61*E61))
D64: To collection | E64: £ | F64: =SUM(F5:F61) -> 41894
F69: =IF(C69="","",(C69*E69))
F70: =IF(C70="","",(C70*E70))
F71: =IF(C71="","",(C71*E71))
F72: =IF(C72="","",(C72*E72))
F73: =IF(C73="","",(C73*E73))
F81: =IF(C81="","",(C81*E81))
F83: =IF(C83="","",(C83*E83))
F85: =IF(C85="","",(C85*E85))
F87: =IF(C87="","",(C87*E87))
F89: =IF(C89="","",(C89*E89))
F91: =IF(C91="","",(C91*E91))
F93: =IF(C93="","",(C93*E93))
... F122: =IF(C122="","",(C122*E122))
D125: To collection | E125: £ | F125: =SUM(F66:F115) -> 0
